{"RecipeGUID":"aa83c059a6c14e7299900ee27d38c169","VM":{"Recipe":{"RecipeID":100310,"GUID":"aa83c059a6c14e7299900ee27d38c169","PreviousGUID":"00000000000000000000000000000000","Efficiency":55.0,"Author":"Tom Kelshaw","Name":"Coconut Summer S v1","WortSize":null,"BatchSize":3.0,"CreationDate":"2017-09-22T02:31:07.163","ABV":4.8,"IBU":34.0,"SRM":38.0,"FG":1.0092,"OG":1.0461,"Version":1,"StyleID":138,"BeerStyle":{"StyleID":138,"CatNumCode":"16","CatLettCode":"A","StyleNameCode":"Sweet Stout","MaxABV":6.0,"MaxSRM":40.0,"MaxIBU":40.0,"MaxFG":1.024,"MaxOG":1.06,"MinABV":4.0,"MinSRM":30.0,"MinIBU":20.0,"MinFG":1.012,"MinOG":1.044,"StyleGuide":"BJCP 2015"},"MashProfile":null,"Notes":"1.00 Whirlfloc @ 15 min. \n1.00 tsp Yeast Nutrient @ 15 min\n0.25 lbs. Toasted Coconut @ Fermentor\n1.00 Vanilla Beans @ Fermentor\n.125 lb Lactose @ Keg\n1 cup cold brew @ Keg\n1 bag coconut @ Keg for 4-5 days","SyncStatus":true,"H2O":4.06,"RecipeFile":null,"Locked":true,"Shared":true,"OriginalName":"Coconut Summer Stout","OriginalAuthor":"Tom Kelshaw on 6/17/2017","TastingNotes":"A dark, balanced, medium-bodied Sweet Stout.","BoilSize":null,"Deleted":false,"Imported":true,"OriginalAuthorID":8665,"WhirlpoolTemp":null,"BoilTemp":207,"BoilTime":60,"MashTime":90,"MashTemp":152,"MashType":0,"IsFirstWort":false,"Errors":[{"Type":0,"Description":"There can't be any duplicate fermentables."}],"Warnings":[],"Fermentables":[{"Amount":4.6,"ColorPts":0.88667202096631015,"Errors":[],"PotentialGravity":29.11815595082179965712000,"FermentableID":19,"Name":"American Two-Row Pale","Color":1.8,"Yield":36.8,"FermentableType":"Grain"},{"Amount":1.0,"ColorPts":0.23558918431472012,"Errors":[],"PotentialGravity":5.62478555997088655484000,"FermentableID":95,"Name":"Flaked Oats","Color":2.2,"Yield":32.7,"FermentableType":"OtherGrain"},{"Amount":0.25,"ColorPts":0.95038818672415493,"Errors":[],"PotentialGravity":1.419097274304583754112000,"FermentableID":167,"Name":"German CaraMunich","Color":35.5,"Yield":33.0,"FermentableType":"Grain"},{"Amount":0.25,"ColorPts":9.37002437615364,"Errors":[],"PotentialGravity":1.186881356691107166894000,"FermentableID":4,"Name":"American Chocolate","Color":350.0,"Yield":27.6,"FermentableType":"Grain"},{"Amount":0.25,"ColorPts":14.724324019670005,"Errors":[],"PotentialGravity":1.655613486688681046464000,"FermentableID":141,"Name":"Midnight Wheat","Color":550.0,"Yield":38.5,"FermentableType":"Grain"},{"Amount":0.25,"ColorPts":8.0314494652745481,"Errors":[],"PotentialGravity":1.419097274304583754112000,"FermentableID":15,"Name":"American Roasted Barley","Color":300.0,"Yield":33.0,"FermentableType":"Grain"},{"Amount":1.0,"ColorPts":3.8015527468966197,"Errors":[],"PotentialGravity":5.67638909721831657644000,"FermentableID":167,"Name":"German CaraMunich","Color":35.5,"Yield":33.0,"FermentableType":"Grain"}],"Hops":[{"Location":2,"Amount":0.33,"IBU":27.7519341,"Time":60.0,"BoilUse":0,"Errors":[],"AdjunctRound":1,"HopID":14,"Name":"Columbus","Alpha":15.4},{"Location":3,"Amount":0.1,"IBU":0.0271051861,"Time":15.0,"BoilUse":0,"Errors":[],"AdjunctRound":1,"HopID":82,"Name":"Other (See Notes)","Alpha":0.1},{"Location":4,"Amount":0.33,"IBU":6.2945385,"Time":7.0,"BoilUse":0,"Errors":[],"AdjunctRound":1,"HopID":58,"Name":"Simcoe","Alpha":13.0}],"DryHops":[],"WhirlpoolHops":[],"Adjuncts":[{"Location":5,"Amount":1.5,"Time":5,"Units":null,"BoilUse":4,"Errors":[],"AdjunctRound":1,"AdjunctID":77,"Name":"Lactose","Use":"Other","AdjunctType":"Other"}],"WhirlpoolAdjuncts":[],"DryAdjuncts":[],"Yeast":{"YeastID":113,"Name":"SafAle","Laboratory":"Fermentis","ProductID":"S-04","MinAtten":75.0,"MaxAtten":85.0,"MinTemp":59.0,"MaxTemp":68.0,"ExpectedAtten":80.0,"ExpectedTemp":63.0},"Amendments":[],"MachineSteps":[{"ID":100310,"Step":0,"Name":"Heat Water","Temperature":152,"Time":0,"Drain":0,"StepLocation":0},{"ID":100310,"Step":1,"Name":"Mash","Temperature":152,"Time":90,"Drain":8,"StepLocation":1},{"ID":100310,"Step":2,"Name":"Heat to Boil","Temperature":207,"Time":0,"Drain":0,"StepLocation":0},{"ID":100310,"Step":3,"Name":"Boil Adjunct 1","Temperature":207,"Time":45,"Drain":0,"StepLocation":2},{"ID":100310,"Step":4,"Name":"Boil Adjunct 2","Temperature":207,"Time":8,"Drain":0,"StepLocation":3},{"ID":100310,"Step":5,"Name":"Boil Adjunct 3","Temperature":207,"Time":7,"Drain":5,"StepLocation":4},{"ID":100310,"Step":6,"Name":"Connect Chiller","Temperature":0,"Time":0,"Drain":0,"StepLocation":6},{"ID":100310,"Step":7,"Name":"Chill","Temperature":63,"Time":10,"Drain":10,"StepLocation":0}],"FermentationSteps":[{"Step":1,"Name":"Fermentation","Temp":63.0,"Days":10.0,"Hours":0.0,"Minutes":0},{"Step":2,"Name":"Crash Chill","Temp":44.0,"Days":0.0,"Hours":0.0,"Minutes":0}],"FermentationType":0,"BoilSteps":[{"Name":"Adjunct 1","Temp":207,"Time":60,"BoilTime":45,"Ramp":true,"IsWhirlpool":false,"AdjunctRound":1,"Location":2,"Errors":[]},{"Name":"Adjunct 2","Temp":207,"Time":15,"BoilTime":8,"Ramp":false,"IsWhirlpool":false,"AdjunctRound":1,"Location":3,"Errors":[]},{"Name":"Adjunct 3","Temp":207,"Time":7,"BoilTime":2,"Ramp":false,"IsWhirlpool":false,"AdjunctRound":1,"Location":4,"Errors":[]},{"Name":"Adjunct 4","Temp":207,"Time":5,"BoilTime":5,"Ramp":false,"IsWhirlpool":false,"AdjunctRound":1,"Location":5,"Errors":[]}],"MashSteps":[{"Name":"Single Step Infusion Mash","Temp":152.0,"Time":90.0,"Style":"Infusion","Errors":[]}],"WhirlpoolSteps":[],"IsMetric":false,"SessionCount":0,"CrafterVersion":1,"IsBiB":false,"RecipeType":0,"HumanBrewingSteps":{"FillKeg":"Fill keg with 4.06 Gal water","LoadWaterAmendments":"Load selected water amendments (generally dry ingredients go in with milled grain, liquid ingredients in start water, your recipe may vary)","LoadMash":"Mill grain and load into mash compartment","LoadAdjuncts":"Load hops and other boil/whirlpool additions into adjunct compartments:","LoadFermentationAdditions":"Load dry hops and fermentation additions into fermentation keg:","Mash":[{"Name":"American Two-Row Pale","Units":"lbs","Amount":4.6},{"Name":"Flaked Oats","Units":"lbs","Amount":1.0},{"Name":"German CaraMunich","Units":"lbs","Amount":0.25},{"Name":"American Chocolate","Units":"lbs","Amount":0.25},{"Name":"Midnight Wheat","Units":"lbs","Amount":0.25},{"Name":"American Roasted Barley","Units":"lbs","Amount":0.25},{"Name":"German CaraMunich","Units":"lbs","Amount":1.0}],"FermentationAdditions":[],"AdjunctRounds":[{"Round":1,"AddInTime":0,"Adjuncts1":[{"Name":"Columbus","Units":"oz","Amount":0.33}],"Adjuncts2":[{"Name":"Other (See Notes)","Units":"oz","Amount":0.1}],"Adjuncts3":[{"Name":"Simcoe","Units":"oz","Amount":0.33}],"Adjuncts4":[{"Name":"Lactose","Units":"oz","Amount":1.5}]}],"IsMetric":false,"TotalRounds":1},"ZKit":false},"Content":{"Sections":[{"Title":"WATER","Stats":[{"Item1":"Starting Water","Item2":"4.06 gal Water (33.86 lbs)"},{"Item1":"Batch Size","Item2":"3 Gal"}],"Tables":[]},{"Title":"MASH","Stats":[{"Item1":"Mash Type","Item2":"Single Step Infusion"}],"Tables":[{"Title":"Mash Steps","Cols":[{"Val":"Step","Width":"40%"},{"Val":"Temp(째F)","Width":"20%"},{"Val":"Time(mins)","Width":"20%"},{"Val":"","Width":"20%"}],"Rows":[[{"Val":"Single Step Infusion Mash","Width":"40%"},{"Val":"152","Width":"20%"},{"Val":"90","Width":"20%"},{"Val":"","Width":"20%"}]]},{"Title":"Fermentables","Cols":[{"Val":"Ingredient","Width":"40%"},{"Val":"Amount(lbs)","Width":"20%"},{"Val":"Gravity(pts)","Width":"20%"},{"Val":"Color(pts)","Width":"20%"}],"Rows":[[{"Val":"American Two-Row Pale","Width":"40%"},{"Val":"4.6","Width":"20%"},{"Val":"1.037","Width":"20%"},{"Val":"0.89","Width":"20%"}],[{"Val":"Flaked Oats","Width":"40%"},{"Val":"1","Width":"20%"},{"Val":"1.033","Width":"20%"},{"Val":"0.24","Width":"20%"}],[{"Val":"German CaraMunich","Width":"40%"},{"Val":"0.25","Width":"20%"},{"Val":"1.033","Width":"20%"},{"Val":"0.95","Width":"20%"}],[{"Val":"American Chocolate","Width":"40%"},{"Val":"0.25","Width":"20%"},{"Val":"1.028","Width":"20%"},{"Val":"9.37","Width":"20%"}],[{"Val":"Midnight Wheat","Width":"40%"},{"Val":"0.25","Width":"20%"},{"Val":"1.038","Width":"20%"},{"Val":"14.72","Width":"20%"}],[{"Val":"American Roasted Barley","Width":"40%"},{"Val":"0.25","Width":"20%"},{"Val":"1.033","Width":"20%"},{"Val":"8.03","Width":"20%"}],[{"Val":"German CaraMunich","Width":"40%"},{"Val":"1","Width":"20%"},{"Val":"1.033","Width":"20%"},{"Val":"3.80","Width":"20%"}]]}]},{"Title":"BOIL","Stats":[{"Item1":"Boil Time(mins)","Item2":"60"}],"Tables":[{"Title":"Boil Steps","Cols":[{"Val":"Step","Width":"40%"},{"Val":"Temp(째F)","Width":"20%"},{"Val":"Time(mins)","Width":"20%"},{"Val":"Ramp","Width":"20%"}],"Rows":[[{"Val":"Adjunct 1","Width":"40%"},{"Val":"207","Width":"20%"},{"Val":"60","Width":"20%"},{"Val":"Yes","Width":"20%"}],[{"Val":"Adjunct 2","Width":"40%"},{"Val":"207","Width":"20%"},{"Val":"15","Width":"20%"},{"Val":"No","Width":"20%"}],[{"Val":"Adjunct 3","Width":"40%"},{"Val":"207","Width":"20%"},{"Val":"7","Width":"20%"},{"Val":"No","Width":"20%"}],[{"Val":"Adjunct 4","Width":"40%"},{"Val":"207","Width":"20%"},{"Val":"5","Width":"20%"},{"Val":"No","Width":"20%"}]]},{"Title":"Hops","Cols":[{"Val":"Ingredient","Width":"40%"},{"Val":"Amount(oz)","Width":"20%"},{"Val":"AA(%)","Width":"20%"},{"Val":"Time(mins)","Width":"20%"}],"Rows":[[{"Val":"Columbus","Width":"40%"},{"Val":"0.33","Width":"20%"},{"Val":"15.4","Width":"20%"},{"Val":"60","Width":"20%"}],[{"Val":"Other (See Notes)","Width":"40%"},{"Val":"0.1","Width":"20%"},{"Val":"0.1","Width":"20%"},{"Val":"15","Width":"20%"}],[{"Val":"Simcoe","Width":"40%"},{"Val":"0.33","Width":"20%"},{"Val":"13","Width":"20%"},{"Val":"7","Width":"20%"}]]},{"Title":"Other Boil Ingredients","Cols":[{"Val":"Ingredient","Width":"40%"},{"Val":"Amount(oz)","Width":"20%"},{"Val":"Units","Width":"20%"},{"Val":"Time(mins)","Width":"20%"}],"Rows":[[{"Val":"Lactose","Width":"40%"},{"Val":"1.5","Width":"20%"},{"Val":"oz","Width":"20%"},{"Val":"5","Width":"20%"}]]}]},{"Title":"FERMENTATION","Stats":[{"Item1":"Fermentation Type","Item2":"Ale"}],"Tables":[{"Title":"Yeast","Cols":[{"Val":"Name","Width":"40%"},{"Val":"Expected AA%","Width":"20%"},{"Val":"Range Temp(째F)","Width":"20%"},{"Val":"Pitch Temp(mins)","Width":"20%"}],"Rows":[[{"Val":"Fermentis SafAle S-04","Width":"40%"},{"Val":"80","Width":"20%"},{"Val":"59 - 68","Width":"20%"},{"Val":"63","Width":"20%"}]]},{"Title":"Fermentation Steps","Cols":[{"Val":"Step","Width":"40%"},{"Val":"Temp(째F)","Width":"20%"},{"Val":"Days","Width":"20%"},{"Val":"Hours","Width":"20%"}],"Rows":[[{"Val":"Fermentation","Width":"40%"},{"Val":"63","Width":"20%"},{"Val":"10","Width":"20%"},{"Val":"0","Width":"20%"}],[{"Val":"Crash Chill","Width":"40%"},{"Val":"44","Width":"20%"},{"Val":"0","Width":"20%"},{"Val":"0","Width":"20%"}]]}]}],"Stats":{"OG":"1.046","FG":"1.009","IBU":"34","SRM":"38","ABV":"4.8%"},"Style":"BJCP 2015 : 16.A Sweet Stout","SpecialBrewingInstructions":"1.00 Whirlfloc @ 15 min. \n1.00 tsp Yeast Nutrient @ 15 min\n0.25 lbs. Toasted Coconut @ Fermentor\n1.00 Vanilla Beans @ Fermentor\n.125 lb Lactose @ Keg\n1 cup cold brew @ Keg\n1 bag coconut @ Keg for 4-5 days","AverageRating":null,"NumRatings":0,"Reviews":[]},"OwnedByUser":false,"OwnedByPicoBrew":false,"CanAccess":true,"IsAdmin":false,"AdminView":false,"RedirectURL":null,"PicoBrew_ProfileID":0,"User_ProfileID":0,"UserRated":false,"UserCommented":false,"UserRating":null,"CompartmentNames":{"adjunct":{"0":"Pass Through","2":"Adjunct 1","3":"Adjunct 2","4":"Adjunct 3","5":"Adjunct 4"},"step":{"0":"Pass Through","2":"Adjunct 1","3":"Adjunct 2","4":"Adjunct 3","5":"Adjunct 4","1":"Mash","6":"Pause"}}}}