{"RecipeGUID":"c0d51ffc171040b79b38c950af8ebbaa","VM":{"Recipe":{"RecipeID":62519,"GUID":"c0d51ffc171040b79b38c950af8ebbaa","PreviousGUID":"00000000000000000000000000000000","Efficiency":55.0,"Author":"Juergen Pesch","Name":"Tom Pilsener Urq v4","WortSize":null,"BatchSize":2.5,"CreationDate":"2016-06-21T06:20:08.833","ABV":4.9,"IBU":35.0,"SRM":4.0,"FG":1.0147,"OG":1.0525,"Version":1,"StyleID":14,"BeerStyle":{"StyleID":14,"CatNumCode":"2","CatLettCode":"B","StyleNameCode":"Bohemian Pilsener","MaxABV":5.4,"MaxSRM":6.0,"MaxIBU":45.0,"MaxFG":1.017,"MaxOG":1.056,"MinABV":4.2,"MinSRM":3.5,"MinIBU":35.0,"MinFG":1.013,"MinOG":1.044,"StyleGuide":"BJCP 2008"},"MashProfile":null,"Notes":"","SyncStatus":true,"H2O":3.66,"RecipeFile":null,"Locked":true,"Shared":true,"OriginalName":"Tomas Pilsener","OriginalAuthor":"Juergen Pesch on 8/12/2015","TastingNotes":"A very pale, hoppy, medium-bodied Bohemian Pilsener.","BoilSize":null,"Deleted":false,"Imported":true,"OriginalAuthorID":2729,"WhirlpoolTemp":null,"BoilTemp":207,"BoilTime":60,"MashTime":90,"MashTemp":152,"MashType":0,"IsFirstWort":false,"Errors":[],"Warnings":[],"Fermentables":[{"Amount":6.42,"ColorPts":2.1948717948717951,"Errors":[],"PotentialGravity":44.86025699201418803904000,"FermentableID":123,"Name":"Pils Two-row","Color":1.1,"Yield":34.65,"FermentableType":"Grain"},{"Amount":0.24,"ColorPts":0.16410256410256413,"Errors":[],"PotentialGravity":1.197870680694636231683000,"FermentableID":129,"Name":"Rolled Oats","Color":2.2,"Yield":24.75,"FermentableType":"OtherGrain"},{"Amount":0.44,"ColorPts":0.54700854700854706,"Errors":[],"PotentialGravity":3.194321815185700117822000,"FermentableID":133,"Name":"Vienna Malt","Color":4.0,"Yield":36.0,"FermentableType":"Grain"},{"Amount":0.44,"ColorPts":1.0940170940170941,"Errors":[],"PotentialGravity":3.247560512105465111453000,"FermentableID":107,"Name":"German Munich","Color":8.0,"Yield":36.6,"FermentableType":"Grain"}],"Hops":[{"Location":2,"Amount":1.06,"IBU":16.840086,"Time":60.0,"BoilUse":0,"Errors":[],"AdjunctRound":1,"HopID":55,"Name":"Saaz","Alpha":2.6},{"Location":3,"Amount":1.06,"IBU":8.358687,"Time":15.0,"BoilUse":0,"Errors":[],"AdjunctRound":1,"HopID":55,"Name":"Saaz","Alpha":2.6},{"Location":4,"Amount":0.63,"IBU":7.26039648,"Time":10.0,"BoilUse":0,"Errors":[],"AdjunctRound":1,"HopID":25,"Name":"Hallertau","Alpha":5.2},{"Location":5,"Amount":0.35,"IBU":2.217911,"Time":5.0,"BoilUse":0,"Errors":[],"AdjunctRound":1,"HopID":25,"Name":"Hallertau","Alpha":5.2}],"DryHops":[],"WhirlpoolHops":[],"Adjuncts":[{"Location":2,"Amount":0.1,"Time":60,"Units":null,"BoilUse":0,"Errors":[],"AdjunctRound":1,"AdjunctID":48,"Name":"Sea Salt","Use":"Spice","AdjunctType":"Spice"},{"Location":3,"Amount":0.1,"Time":15,"Units":null,"BoilUse":0,"Errors":[],"AdjunctRound":1,"AdjunctID":17,"Name":"Irish Moss","Use":"Fining","AdjunctType":"Fining"}],"WhirlpoolAdjuncts":[],"DryAdjuncts":[],"Yeast":{"YeastID":27,"Name":"Czech Pils","Laboratory":"Wyeast","ProductID":"2278","MinAtten":70.0,"MaxAtten":74.0,"MinTemp":50.0,"MaxTemp":58.0,"ExpectedAtten":72.0,"ExpectedTemp":54.0},"Amendments":[],"MachineSteps":[{"ID":62519,"Step":1,"Name":"Heat Water","Temperature":152,"Time":0,"Drain":0,"StepLocation":0},{"ID":62519,"Step":2,"Name":"Mash","Temperature":152,"Time":90,"Drain":8,"StepLocation":1},{"ID":62519,"Step":3,"Name":"Heat to Boil","Temperature":206,"Time":0,"Drain":0,"StepLocation":0},{"ID":62519,"Step":4,"Name":"Boil Adjunct 1","Temperature":206,"Time":45,"Drain":0,"StepLocation":2},{"ID":62519,"Step":5,"Name":"Boil Adjunct 2","Temperature":206,"Time":5,"Drain":0,"StepLocation":3},{"ID":62519,"Step":6,"Name":"Boil Adjunct 3","Temperature":206,"Time":5,"Drain":0,"StepLocation":4},{"ID":62519,"Step":7,"Name":"Boil Adjunct 4","Temperature":206,"Time":5,"Drain":5,"StepLocation":5},{"ID":62519,"Step":8,"Name":"Connect Chiller","Temperature":32,"Time":0,"Drain":0,"StepLocation":6},{"ID":62519,"Step":9,"Name":"Chill","Temperature":53,"Time":10,"Drain":10,"StepLocation":0}],"FermentationSteps":[{"Step":1,"Name":"Primary Fermentation","Temp":53.0,"Days":37.0,"Hours":0.0,"Minutes":0},{"Step":2,"Name":"Lagering","Temp":35.0,"Days":28.0,"Hours":0.0,"Minutes":0}],"FermentationType":2,"BoilSteps":[{"Name":"Adjunct 1","Temp":207,"Time":60,"BoilTime":45,"Ramp":true,"IsWhirlpool":false,"AdjunctRound":1,"Location":2,"Errors":[]},{"Name":"Adjunct 2","Temp":207,"Time":15,"BoilTime":5,"Ramp":false,"IsWhirlpool":false,"AdjunctRound":1,"Location":3,"Errors":[]},{"Name":"Adjunct 3","Temp":207,"Time":10,"BoilTime":5,"Ramp":false,"IsWhirlpool":false,"AdjunctRound":1,"Location":4,"Errors":[]},{"Name":"Adjunct 4","Temp":207,"Time":5,"BoilTime":5,"Ramp":false,"IsWhirlpool":false,"AdjunctRound":1,"Location":5,"Errors":[]}],"MashSteps":[{"Name":"Single Step Infusion Mash","Temp":152.0,"Time":90.0,"Style":"Infusion","Errors":[]}],"WhirlpoolSteps":[],"IsMetric":false,"SessionCount":0,"CrafterVersion":1,"IsBiB":false,"RecipeType":0,"HumanBrewingSteps":{"FillKeg":"Fill keg with 3.66 Gal water","LoadWaterAmendments":"Load selected water amendments (generally dry ingredients go in with milled grain, liquid ingredients in start water, your recipe may vary)","LoadMash":"Mill grain and load into mash compartment","LoadAdjuncts":"Load hops and other boil/whirlpool additions into adjunct compartments:","LoadFermentationAdditions":"Load dry hops and fermentation additions into fermentation keg:","Mash":[{"Name":"Pils Two-row","Units":"lbs","Amount":6.42},{"Name":"Rolled Oats","Units":"lbs","Amount":0.24},{"Name":"Vienna Malt","Units":"lbs","Amount":0.44},{"Name":"German Munich","Units":"lbs","Amount":0.44}],"FermentationAdditions":[],"AdjunctRounds":[{"Round":1,"AddInTime":0,"Adjuncts1":[{"Name":"Saaz","Units":"oz","Amount":1.06},{"Name":"Sea Salt","Units":"oz","Amount":0.1}],"Adjuncts2":[{"Name":"Saaz","Units":"oz","Amount":1.06},{"Name":"Irish Moss","Units":"oz","Amount":0.1}],"Adjuncts3":[{"Name":"Hallertau","Units":"oz","Amount":0.63}],"Adjuncts4":[{"Name":"Hallertau","Units":"oz","Amount":0.35}]}],"IsMetric":false,"TotalRounds":1},"ZKit":false},"Content":{"Sections":[{"Title":"WATER","Stats":[{"Item1":"Starting Water","Item2":"3.66 gal Water (30.52 lbs)"},{"Item1":"Batch Size","Item2":"2.5 Gal"}],"Tables":[]},{"Title":"MASH","Stats":[{"Item1":"Mash Type","Item2":"Single Step Infusion"}],"Tables":[{"Title":"Mash Steps","Cols":[{"Val":"Step","Width":"40%"},{"Val":"Temp(째F)","Width":"20%"},{"Val":"Time(mins)","Width":"20%"},{"Val":"","Width":"20%"}],"Rows":[[{"Val":"Single Step Infusion Mash","Width":"40%"},{"Val":"152","Width":"20%"},{"Val":"90","Width":"20%"},{"Val":"","Width":"20%"}]]},{"Title":"Fermentables","Cols":[{"Val":"Ingredient","Width":"40%"},{"Val":"Amount(lbs)","Width":"20%"},{"Val":"Gravity(pts)","Width":"20%"},{"Val":"Color(pts)","Width":"20%"}],"Rows":[[{"Val":"Pils Two-row","Width":"40%"},{"Val":"6.42","Width":"20%"},{"Val":"1.035","Width":"20%"},{"Val":"2.19","Width":"20%"}],[{"Val":"Rolled Oats","Width":"40%"},{"Val":"0.24","Width":"20%"},{"Val":"1.025","Width":"20%"},{"Val":"0.16","Width":"20%"}],[{"Val":"Vienna Malt","Width":"40%"},{"Val":"0.44","Width":"20%"},{"Val":"1.036","Width":"20%"},{"Val":"0.55","Width":"20%"}],[{"Val":"German Munich","Width":"40%"},{"Val":"0.44","Width":"20%"},{"Val":"1.037","Width":"20%"},{"Val":"1.09","Width":"20%"}]]}]},{"Title":"BOIL","Stats":[{"Item1":"Boil Time(mins)","Item2":"60"}],"Tables":[{"Title":"Boil Steps","Cols":[{"Val":"Step","Width":"40%"},{"Val":"Temp(째F)","Width":"20%"},{"Val":"Time(mins)","Width":"20%"},{"Val":"Ramp","Width":"20%"}],"Rows":[[{"Val":"Adjunct 1","Width":"40%"},{"Val":"207","Width":"20%"},{"Val":"60","Width":"20%"},{"Val":"Yes","Width":"20%"}],[{"Val":"Adjunct 2","Width":"40%"},{"Val":"207","Width":"20%"},{"Val":"15","Width":"20%"},{"Val":"No","Width":"20%"}],[{"Val":"Adjunct 3","Width":"40%"},{"Val":"207","Width":"20%"},{"Val":"10","Width":"20%"},{"Val":"No","Width":"20%"}],[{"Val":"Adjunct 4","Width":"40%"},{"Val":"207","Width":"20%"},{"Val":"5","Width":"20%"},{"Val":"No","Width":"20%"}]]},{"Title":"Hops","Cols":[{"Val":"Ingredient","Width":"40%"},{"Val":"Amount(oz)","Width":"20%"},{"Val":"AA(%)","Width":"20%"},{"Val":"Time(mins)","Width":"20%"}],"Rows":[[{"Val":"Saaz","Width":"40%"},{"Val":"1.06","Width":"20%"},{"Val":"2.6","Width":"20%"},{"Val":"60","Width":"20%"}],[{"Val":"Saaz","Width":"40%"},{"Val":"1.06","Width":"20%"},{"Val":"2.6","Width":"20%"},{"Val":"15","Width":"20%"}],[{"Val":"Hallertau","Width":"40%"},{"Val":"0.63","Width":"20%"},{"Val":"5.2","Width":"20%"},{"Val":"10","Width":"20%"}],[{"Val":"Hallertau","Width":"40%"},{"Val":"0.35","Width":"20%"},{"Val":"5.2","Width":"20%"},{"Val":"5","Width":"20%"}]]},{"Title":"Other Boil Ingredients","Cols":[{"Val":"Ingredient","Width":"40%"},{"Val":"Amount(oz)","Width":"20%"},{"Val":"Units","Width":"20%"},{"Val":"Time(mins)","Width":"20%"}],"Rows":[[{"Val":"Sea Salt","Width":"40%"},{"Val":"0.1","Width":"20%"},{"Val":"oz","Width":"20%"},{"Val":"60","Width":"20%"}],[{"Val":"Irish Moss","Width":"40%"},{"Val":"0.1","Width":"20%"},{"Val":"oz","Width":"20%"},{"Val":"15","Width":"20%"}]]}]},{"Title":"FERMENTATION","Stats":[{"Item1":"Fermentation Type","Item2":"Custom"}],"Tables":[{"Title":"Yeast","Cols":[{"Val":"Name","Width":"40%"},{"Val":"Expected AA%","Width":"20%"},{"Val":"Range Temp(째F)","Width":"20%"},{"Val":"Pitch Temp(mins)","Width":"20%"}],"Rows":[[{"Val":"Wyeast Czech Pils 2278","Width":"40%"},{"Val":"72","Width":"20%"},{"Val":"50 - 58","Width":"20%"},{"Val":"54","Width":"20%"}]]},{"Title":"Fermentation Steps","Cols":[{"Val":"Step","Width":"40%"},{"Val":"Temp(째F)","Width":"20%"},{"Val":"Days","Width":"20%"},{"Val":"Hours","Width":"20%"}],"Rows":[[{"Val":"Primary Fermentation","Width":"40%"},{"Val":"53","Width":"20%"},{"Val":"37","Width":"20%"},{"Val":"0","Width":"20%"}],[{"Val":"Lagering","Width":"40%"},{"Val":"35","Width":"20%"},{"Val":"28","Width":"20%"},{"Val":"0","Width":"20%"}]]}]}],"Stats":{"OG":"1.053","FG":"1.015","IBU":"35","SRM":"4","ABV":"4.9%"},"Style":"BJCP 2008 : 2.B Bohemian Pilsener","SpecialBrewingInstructions":"","AverageRating":9.0,"NumRatings":1,"Reviews":[]},"OwnedByUser":false,"OwnedByPicoBrew":false,"CanAccess":true,"IsAdmin":false,"AdminView":false,"RedirectURL":null,"PicoBrew_ProfileID":0,"User_ProfileID":0,"UserRated":false,"UserCommented":false,"UserRating":null,"CompartmentNames":{"adjunct":{"0":"Pass Through","2":"Adjunct 1","3":"Adjunct 2","4":"Adjunct 3","5":"Adjunct 4"},"step":{"0":"Pass Through","2":"Adjunct 1","3":"Adjunct 2","4":"Adjunct 3","5":"Adjunct 4","1":"Mash","6":"Pause"}}}}