{"RecipeGUID":"19d6e5c595b04bdeba536e6761e193b2","VM":{"Recipe":{"RecipeID":74688,"GUID":"19d6e5c595b04bdeba536e6761e193b2","PreviousGUID":"00000000000000000000000000000000","Efficiency":80.0,"Author":"David Gossage","Name":"Heinielicious","WortSize":null,"BatchSize":2.9,"CreationDate":"2016-11-12T23:32:18.74","ABV":5.7,"IBU":22.0,"SRM":3.0,"FG":1.006,"OG":1.0498,"Version":1,"StyleID":13,"BeerStyle":{"StyleID":13,"CatNumCode":"2","CatLettCode":"A","StyleNameCode":"German Pilsner","MaxABV":5.2,"MaxSRM":5.0,"MaxIBU":45.0,"MaxFG":1.013,"MaxOG":1.05,"MinABV":4.4,"MinSRM":2.0,"MinIBU":25.0,"MinFG":1.008,"MinOG":1.044,"StyleGuide":"BJCP 2008"},"MashProfile":null,"Notes":"start with 3.71 gallons of water","SyncStatus":true,"H2O":3.48,"RecipeFile":null,"Locked":true,"Shared":true,"OriginalName":"Heinielicious","OriginalAuthor":"David Gossage on 11/12/2016","TastingNotes":"A very pale, malty, medium-bodied German Pilsner.","BoilSize":null,"Deleted":false,"Imported":true,"OriginalAuthorID":5510,"WhirlpoolTemp":null,"BoilTemp":207,"BoilTime":60,"MashTime":90,"MashTemp":152,"MashType":2,"IsFirstWort":false,"Errors":[],"Warnings":[],"Fermentables":[{"Amount":5.0,"ColorPts":2.5195968645016795,"Errors":[],"PotentialGravity":48.67309790828410139096000,"FermentableID":108,"Name":"German Pilsener","Color":1.65,"Yield":37.675,"FermentableType":"Grain"},{"Amount":0.13,"ColorPts":0.4804031354983202,"Errors":[],"PotentialGravity":1.126942091715893629036000,"FermentableID":103,"Name":"German Carahell","Color":12.1,"Yield":33.55,"FermentableType":"Grain"}],"Hops":[{"Location":2,"Amount":0.5,"IBU":18.8115444,"Time":60.0,"BoilUse":0,"Errors":[],"AdjunctRound":1,"HopID":42,"Name":"Northern Brewer","Alpha":6.9},{"Location":3,"Amount":0.37,"IBU":3.10429215,"Time":15.0,"BoilUse":0,"Errors":[],"AdjunctRound":1,"HopID":25,"Name":"Hallertau","Alpha":3.1},{"Location":4,"Amount":0.13,"IBU":0.4382461,"Time":5.0,"BoilUse":0,"Errors":[],"AdjunctRound":1,"HopID":25,"Name":"Hallertau","Alpha":3.1}],"DryHops":[],"WhirlpoolHops":[],"Adjuncts":[{"Location":3,"Amount":0.1,"Time":15,"Units":null,"BoilUse":0,"Errors":[],"AdjunctRound":1,"AdjunctID":17,"Name":"Irish Moss","Use":"Fining","AdjunctType":"Fining"}],"WhirlpoolAdjuncts":[],"DryAdjuncts":[],"Yeast":{"YeastID":118,"Name":"SafLager","Laboratory":"Fermentis","ProductID":"W-34/70","MinAtten":79.0,"MaxAtten":87.0,"MinTemp":53.0,"MaxTemp":59.0,"ExpectedAtten":88.0,"ExpectedTemp":56.0},"Amendments":[],"MachineSteps":[{"ID":74688,"Step":0,"Name":"Heat to Temp","Temperature":102,"Time":0,"Drain":0,"StepLocation":0},{"ID":74688,"Step":1,"Name":"Dough In","Temperature":102,"Time":20,"Drain":8,"StepLocation":1},{"ID":74688,"Step":2,"Name":"Heat to Mash","Temperature":152,"Time":0,"Drain":0,"StepLocation":0},{"ID":74688,"Step":3,"Name":"Mash 1","Temperature":152,"Time":30,"Drain":0,"StepLocation":1},{"ID":74688,"Step":4,"Name":"Mash 2","Temperature":154,"Time":60,"Drain":8,"StepLocation":1},{"ID":74688,"Step":5,"Name":"Heat to MO","Temperature":175,"Time":0,"Drain":0,"StepLocation":0},{"ID":74688,"Step":6,"Name":"Mash Out","Temperature":175,"Time":10,"Drain":6,"StepLocation":1},{"ID":74688,"Step":7,"Name":"Heat to Boil","Temperature":207,"Time":0,"Drain":0,"StepLocation":0},{"ID":74688,"Step":8,"Name":"Boil Adjunct 1","Temperature":207,"Time":45,"Drain":0,"StepLocation":2},{"ID":74688,"Step":9,"Name":"Boil Adjunct 2","Temperature":207,"Time":10,"Drain":0,"StepLocation":3},{"ID":74688,"Step":10,"Name":"Boil Adjunct 3","Temperature":207,"Time":5,"Drain":5,"StepLocation":4},{"ID":74688,"Step":11,"Name":"Connect Chiller","Temperature":0,"Time":0,"Drain":0,"StepLocation":6},{"ID":74688,"Step":12,"Name":"Chill","Temperature":56,"Time":10,"Drain":10,"StepLocation":0}],"FermentationSteps":[{"Step":1,"Name":"Primary Fermentation","Temp":56.0,"Days":21.0,"Hours":0.0,"Minutes":0},{"Step":2,"Name":"Lagering","Temp":35.0,"Days":28.0,"Hours":0.0,"Minutes":0}],"FermentationType":1,"BoilSteps":[{"Name":"Adjunct 1","Temp":207,"Time":60,"BoilTime":45,"Ramp":true,"IsWhirlpool":false,"AdjunctRound":1,"Location":2,"Errors":[]},{"Name":"Adjunct 2","Temp":207,"Time":15,"BoilTime":10,"Ramp":false,"IsWhirlpool":false,"AdjunctRound":1,"Location":3,"Errors":[]},{"Name":"Adjunct 3","Temp":207,"Time":5,"BoilTime":5,"Ramp":false,"IsWhirlpool":false,"AdjunctRound":1,"Location":4,"Errors":[]}],"MashSteps":[{"Name":"Dough In","Temp":102.0,"Time":20.0,"Style":"Infusion","Errors":[]},{"Name":"Mash 1","Temp":152.0,"Time":30.0,"Style":"Infusion","Errors":[]},{"Name":"Mash 2","Temp":154.0,"Time":60.0,"Style":"Infusion","Errors":[]},{"Name":"Mash Out","Temp":175.0,"Time":10.0,"Style":"Infusion","Errors":[]}],"WhirlpoolSteps":[],"IsMetric":false,"SessionCount":0,"CrafterVersion":1,"IsBiB":false,"RecipeType":0,"HumanBrewingSteps":{"FillKeg":"Fill keg with 3.48 Gal water","LoadWaterAmendments":"Load selected water amendments (generally dry ingredients go in with milled grain, liquid ingredients in start water, your recipe may vary)","LoadMash":"Mill grain and load into mash compartment","LoadAdjuncts":"Load hops and other boil/whirlpool additions into adjunct compartments:","LoadFermentationAdditions":"Load dry hops and fermentation additions into fermentation keg:","Mash":[{"Name":"German Pilsener","Units":"lbs","Amount":5.0},{"Name":"German Carahell","Units":"lbs","Amount":0.13}],"FermentationAdditions":[],"AdjunctRounds":[{"Round":1,"AddInTime":0,"Adjuncts1":[{"Name":"Northern Brewer","Units":"oz","Amount":0.5}],"Adjuncts2":[{"Name":"Hallertau","Units":"oz","Amount":0.37},{"Name":"Irish Moss","Units":"oz","Amount":0.1}],"Adjuncts3":[{"Name":"Hallertau","Units":"oz","Amount":0.13}],"Adjuncts4":[]}],"IsMetric":false,"TotalRounds":1},"ZKit":false},"Content":{"Sections":[{"Title":"WATER","Stats":[{"Item1":"Starting Water","Item2":"3.48 gal Water (29.02 lbs)"},{"Item1":"Batch Size","Item2":"2.9 Gal"}],"Tables":[]},{"Title":"MASH","Stats":[{"Item1":"Mash Type","Item2":"Custom"}],"Tables":[{"Title":"Mash Steps","Cols":[{"Val":"Step","Width":"40%"},{"Val":"Temp(째F)","Width":"20%"},{"Val":"Time(mins)","Width":"20%"},{"Val":"","Width":"20%"}],"Rows":[[{"Val":"Dough In","Width":"40%"},{"Val":"102","Width":"20%"},{"Val":"20","Width":"20%"},{"Val":"","Width":"20%"}],[{"Val":"Mash 1","Width":"40%"},{"Val":"152","Width":"20%"},{"Val":"30","Width":"20%"},{"Val":"","Width":"20%"}],[{"Val":"Mash 2","Width":"40%"},{"Val":"154","Width":"20%"},{"Val":"60","Width":"20%"},{"Val":"","Width":"20%"}],[{"Val":"Mash Out","Width":"40%"},{"Val":"175","Width":"20%"},{"Val":"10","Width":"20%"},{"Val":"","Width":"20%"}]]},{"Title":"Fermentables","Cols":[{"Val":"Ingredient","Width":"40%"},{"Val":"Amount(lbs)","Width":"20%"},{"Val":"Gravity(pts)","Width":"20%"},{"Val":"Color(pts)","Width":"20%"}],"Rows":[[{"Val":"German Pilsener","Width":"40%"},{"Val":"5","Width":"20%"},{"Val":"1.038","Width":"20%"},{"Val":"2.52","Width":"20%"}],[{"Val":"German Carahell","Width":"40%"},{"Val":"0.13","Width":"20%"},{"Val":"1.034","Width":"20%"},{"Val":"0.48","Width":"20%"}]]}]},{"Title":"BOIL","Stats":[{"Item1":"Boil Time(mins)","Item2":"60"}],"Tables":[{"Title":"Boil Steps","Cols":[{"Val":"Step","Width":"40%"},{"Val":"Temp(째F)","Width":"20%"},{"Val":"Time(mins)","Width":"20%"},{"Val":"Ramp","Width":"20%"}],"Rows":[[{"Val":"Adjunct 1","Width":"40%"},{"Val":"207","Width":"20%"},{"Val":"60","Width":"20%"},{"Val":"Yes","Width":"20%"}],[{"Val":"Adjunct 2","Width":"40%"},{"Val":"207","Width":"20%"},{"Val":"15","Width":"20%"},{"Val":"No","Width":"20%"}],[{"Val":"Adjunct 3","Width":"40%"},{"Val":"207","Width":"20%"},{"Val":"5","Width":"20%"},{"Val":"No","Width":"20%"}]]},{"Title":"Hops","Cols":[{"Val":"Ingredient","Width":"40%"},{"Val":"Amount(oz)","Width":"20%"},{"Val":"AA(%)","Width":"20%"},{"Val":"Time(mins)","Width":"20%"}],"Rows":[[{"Val":"Northern Brewer","Width":"40%"},{"Val":"0.5","Width":"20%"},{"Val":"6.9","Width":"20%"},{"Val":"60","Width":"20%"}],[{"Val":"Hallertau","Width":"40%"},{"Val":"0.37","Width":"20%"},{"Val":"3.1","Width":"20%"},{"Val":"15","Width":"20%"}],[{"Val":"Hallertau","Width":"40%"},{"Val":"0.13","Width":"20%"},{"Val":"3.1","Width":"20%"},{"Val":"5","Width":"20%"}]]},{"Title":"Other Boil Ingredients","Cols":[{"Val":"Ingredient","Width":"40%"},{"Val":"Amount(oz)","Width":"20%"},{"Val":"Units","Width":"20%"},{"Val":"Time(mins)","Width":"20%"}],"Rows":[[{"Val":"Irish Moss","Width":"40%"},{"Val":"0.1","Width":"20%"},{"Val":"oz","Width":"20%"},{"Val":"15","Width":"20%"}]]}]},{"Title":"FERMENTATION","Stats":[{"Item1":"Fermentation Type","Item2":"Lager"}],"Tables":[{"Title":"Yeast","Cols":[{"Val":"Name","Width":"40%"},{"Val":"Expected AA%","Width":"20%"},{"Val":"Range Temp(째F)","Width":"20%"},{"Val":"Pitch Temp(mins)","Width":"20%"}],"Rows":[[{"Val":"Fermentis SafLager W-34/70","Width":"40%"},{"Val":"88","Width":"20%"},{"Val":"53 - 59","Width":"20%"},{"Val":"56","Width":"20%"}]]},{"Title":"Fermentation Steps","Cols":[{"Val":"Step","Width":"40%"},{"Val":"Temp(째F)","Width":"20%"},{"Val":"Days","Width":"20%"},{"Val":"Hours","Width":"20%"}],"Rows":[[{"Val":"Primary Fermentation","Width":"40%"},{"Val":"56","Width":"20%"},{"Val":"21","Width":"20%"},{"Val":"0","Width":"20%"}],[{"Val":"Lagering","Width":"40%"},{"Val":"35","Width":"20%"},{"Val":"28","Width":"20%"},{"Val":"0","Width":"20%"}]]}]}],"Stats":{"OG":"1.05","FG":"1.006","IBU":"22","SRM":"3","ABV":"5.7%"},"Style":"BJCP 2008 : 2.A German Pilsner","SpecialBrewingInstructions":"start with 3.71 gallons of water","AverageRating":null,"NumRatings":0,"Reviews":[]},"OwnedByUser":false,"OwnedByPicoBrew":false,"CanAccess":true,"IsAdmin":false,"AdminView":false,"RedirectURL":null,"PicoBrew_ProfileID":0,"User_ProfileID":0,"UserRated":false,"UserCommented":false,"UserRating":null,"CompartmentNames":{"adjunct":{"0":"Pass Through","2":"Adjunct 1","3":"Adjunct 2","4":"Adjunct 3","5":"Adjunct 4"},"step":{"0":"Pass Through","2":"Adjunct 1","3":"Adjunct 2","4":"Adjunct 3","5":"Adjunct 4","1":"Mash","6":"Pause"}}}}