{"RecipeGUID":"31887bc472794ef89425df654425bb4a","VM":{"Recipe":{"RecipeID":135628,"GUID":"31887bc472794ef89425df654425bb4a","PreviousGUID":null,"Efficiency":55.0,"Author":"Bmelton","Name":"Le Petite Orange","WortSize":null,"BatchSize":1.32,"CreationDate":"2019-07-17T12:28:02.04","ABV":7.1,"IBU":24.0,"SRM":14.0,"FG":1.013,"OG":1.065,"Version":1,"StyleID":74,"BeerStyle":{"StyleID":74,"CatNumCode":"18","CatLettCode":"B","StyleNameCode":"Belgian Dubbel","MaxABV":7.6,"MaxSRM":17.0,"MaxIBU":25.0,"MaxFG":1.018,"MaxOG":1.075,"MinABV":6.0,"MinSRM":10.0,"MinIBU":15.0,"MinFG":1.008,"MinOG":1.062,"StyleGuide":"BJCP 2008"},"MashProfile":null,"Notes":"","SyncStatus":true,"H2O":1.97,"RecipeFile":null,"Locked":true,"Shared":true,"OriginalName":"Le Petite Orange","OriginalAuthor":"Bmelton","TastingNotes":"A Belgian Dubbel without the deep dark chocolate maltiness, La Petite Orange is rich with caramel sweetness and a full body with rich esters of cherry, strawberry, hints of tropical flavors.","BoilSize":null,"Deleted":false,"Imported":true,"OriginalAuthorID":21471,"WhirlpoolTemp":null,"BoilTemp":203,"BoilTime":60,"MashTime":70,"MashTemp":149,"MashType":0,"IsFirstWort":false,"Errors":[],"Warnings":[{"Type":11,"Description":"WARNING: Your mash volume may be too low and may cause foaming.  We suggest increasing the batch size or increasing the amount of fermentables."}],"Fermentables":[{"Amount":3.0,"ColorPts":1.1348795316370186,"Errors":[],"PotentialGravity":45.76275410691006945244000,"FermentableID":36,"Name":"Belgian Pils","Color":1.5,"Yield":36.0,"FermentableType":"Grain"},{"Amount":0.25,"ColorPts":0.50439090294978606,"Errors":[],"PotentialGravity":3.49576593872229787484000,"FermentableID":30,"Name":"Belgian Carapils","Color":8.0,"Yield":33.0,"FermentableType":"Grain"},{"Amount":0.25,"ColorPts":1.3870749831119116,"Errors":[],"PotentialGravity":3.146189344850068087356000,"FermentableID":31,"Name":"Belgian Caravienne","Color":22.0,"Yield":29.7,"FermentableType":"Grain"},{"Amount":0.125,"ColorPts":0.78811078585904071,"Errors":[],"PotentialGravity":1.573094672425034043678000,"FermentableID":25,"Name":"Belgian Aromatic","Color":25.0,"Yield":29.7,"FermentableType":"Grain"},{"Amount":0.125,"ColorPts":0.72821436613375368,"Errors":[],"PotentialGravity":1.573094672425034043678000,"FermentableID":26,"Name":"Belgian Biscuit","Color":23.1,"Yield":29.7,"FermentableType":"Grain"},{"Amount":0.5,"ColorPts":9.4573294303084889,"Errors":[],"PotentialGravity":9.44916126466750949802000,"FermentableID":27,"Name":"Belgian Candi Sugar Amber","Color":75.0,"Yield":44.6,"FermentableType":"Sugar"}],"Hops":[{"Location":2,"Amount":0.5,"IBU":26.6765156,"Time":60.0,"BoilUse":0,"Errors":[],"AdjunctRound":1,"HopID":64,"Name":"Styrian Goldings","Alpha":5.5},{"Location":2,"Amount":0.12,"IBU":13.6195736,"Time":60.0,"BoilUse":0,"Errors":[],"AdjunctRound":1,"HopID":175,"Name":"Loral","Alpha":11.7}],"DryHops":[],"WhirlpoolHops":[],"Adjuncts":[{"Location":2,"Amount":0.2,"Time":60,"Units":null,"BoilUse":0,"Errors":[],"AdjunctRound":1,"AdjunctID":8,"Name":"Coriander Seed","Use":"Spice","AdjunctType":"Spice"},{"Location":3,"Amount":2.0,"Time":10,"Units":null,"BoilUse":0,"Errors":[],"AdjunctRound":1,"AdjunctID":45,"Name":"Orange Zest","Use":"Spice","AdjunctType":"Spice"}],"WhirlpoolAdjuncts":[],"DryAdjuncts":[],"Yeast":{"YeastID":113,"Name":"SafAle","Laboratory":"Fermentis","ProductID":"S-04","MinAtten":75.0,"MaxAtten":85.0,"MinTemp":59.0,"MaxTemp":68.0,"ExpectedAtten":80.0,"ExpectedTemp":63.0},"Amendments":[],"MachineSteps":[{"ID":135628,"Step":0,"Name":"Heat to Single S...","Temperature":149,"Time":0,"Drain":0,"StepLocation":0},{"ID":135628,"Step":1,"Name":"Single Step Infu...","Temperature":149,"Time":70,"Drain":8,"StepLocation":1},{"ID":135628,"Step":2,"Name":"Heat to Boil","Temperature":203,"Time":0,"Drain":0,"StepLocation":0},{"ID":135628,"Step":3,"Name":"Boil Adjunct 1","Temperature":203,"Time":50,"Drain":8,"StepLocation":2},{"ID":135628,"Step":4,"Name":"Heat to Boil Adj...","Temperature":207,"Time":0,"Drain":0,"StepLocation":0},{"ID":135628,"Step":5,"Name":"Boil Adjunct 2","Temperature":207,"Time":10,"Drain":5,"StepLocation":3}],"FermentationSteps":[{"Step":1,"Name":"Fermentation","Temp":63.0,"Days":10.0,"Hours":0.0,"Minutes":0},{"Step":2,"Name":"Crash Chill","Temp":44.0,"Days":0.0,"Hours":0.0,"Minutes":0}],"FermentationType":0,"BoilSteps":[{"Name":"Adjunct 1","Temp":203,"Time":60,"BoilTime":50,"Ramp":true,"IsWhirlpool":false,"AdjunctRound":1,"Location":2,"Errors":[]},{"Name":"Adjunct 2","Temp":207,"Time":10,"BoilTime":10,"Ramp":false,"IsWhirlpool":false,"AdjunctRound":1,"Location":3,"Errors":[]}],"MashSteps":[{"Name":"Single Step Infusion Mash","Temp":149.0,"Time":70.0,"Style":"Infusion","Errors":[]}],"WhirlpoolSteps":[],"IsMetric":false,"SessionCount":0,"CrafterVersion":1,"IsBiB":false,"RecipeType":0,"HumanBrewingSteps":{"FillKeg":"Fill keg with 1.97 Gal water","LoadWaterAmendments":"Load selected water amendments (generally dry ingredients go in with milled grain, liquid ingredients in start water, your recipe may vary)","LoadMash":"Mill grain and load into mash compartment","LoadAdjuncts":"Load hops and other boil/whirlpool additions into adjunct compartments:","LoadFermentationAdditions":"Load dry hops and fermentation additions into fermentation keg:","Mash":[{"Name":"Belgian Pils","Units":"lbs","Amount":3.0},{"Name":"Belgian Carapils","Units":"lbs","Amount":0.25},{"Name":"Belgian Caravienne","Units":"lbs","Amount":0.25},{"Name":"Belgian Aromatic","Units":"lbs","Amount":0.125},{"Name":"Belgian Biscuit","Units":"lbs","Amount":0.125},{"Name":"Belgian Candi Sugar Amber","Units":"lbs","Amount":0.5}],"FermentationAdditions":[],"AdjunctRounds":[{"Round":1,"AddInTime":0,"Adjuncts1":[{"Name":"Styrian Goldings","Units":"oz","Amount":0.5},{"Name":"Loral","Units":"oz","Amount":0.12},{"Name":"Coriander Seed","Units":"oz","Amount":0.2}],"Adjuncts2":[{"Name":"Orange Zest","Units":"oz","Amount":2.0}],"Adjuncts3":[],"Adjuncts4":[]}],"IsMetric":false,"TotalRounds":1},"ZKit":false},"Content":{"Sections":[{"Title":"WATER","Stats":[{"Item1":"Starting Water","Item2":"1.97 gal Water (16.43 lbs)"},{"Item1":"Batch Size","Item2":"1.32 Gal"}],"Tables":[]},{"Title":"MASH","Stats":[{"Item1":"Mash Type","Item2":"Single Step Infusion"}],"Tables":[{"Title":"Mash Steps","Cols":[{"Val":"Step","Width":"40%"},{"Val":"Temp(째F)","Width":"20%"},{"Val":"Time(mins)","Width":"20%"},{"Val":"","Width":"20%"}],"Rows":[[{"Val":"Single Step Infusion Mash","Width":"40%"},{"Val":"149","Width":"20%"},{"Val":"70","Width":"20%"},{"Val":"","Width":"20%"}]]},{"Title":"Fermentables","Cols":[{"Val":"Ingredient","Width":"40%"},{"Val":"Amount(lbs)","Width":"20%"},{"Val":"Gravity(pts)","Width":"20%"},{"Val":"Color(pts)","Width":"20%"}],"Rows":[[{"Val":"Belgian Pils","Width":"40%"},{"Val":"3","Width":"20%"},{"Val":"1.036","Width":"20%"},{"Val":"1.13","Width":"20%"}],[{"Val":"Belgian Carapils","Width":"40%"},{"Val":"0.25","Width":"20%"},{"Val":"1.033","Width":"20%"},{"Val":"0.50","Width":"20%"}],[{"Val":"Belgian Caravienne","Width":"40%"},{"Val":"0.25","Width":"20%"},{"Val":"1.03","Width":"20%"},{"Val":"1.39","Width":"20%"}],[{"Val":"Belgian Aromatic","Width":"40%"},{"Val":"0.125","Width":"20%"},{"Val":"1.03","Width":"20%"},{"Val":"0.79","Width":"20%"}],[{"Val":"Belgian Biscuit","Width":"40%"},{"Val":"0.125","Width":"20%"},{"Val":"1.03","Width":"20%"},{"Val":"0.73","Width":"20%"}],[{"Val":"Belgian Candi Sugar Amber","Width":"40%"},{"Val":"0.5","Width":"20%"},{"Val":"1.045","Width":"20%"},{"Val":"9.46","Width":"20%"}]]}]},{"Title":"BOIL","Stats":[{"Item1":"Boil Time(mins)","Item2":"60"}],"Tables":[{"Title":"Boil Steps","Cols":[{"Val":"Step","Width":"40%"},{"Val":"Temp(째F)","Width":"20%"},{"Val":"Time(mins)","Width":"20%"},{"Val":"Ramp","Width":"20%"}],"Rows":[[{"Val":"Adjunct 1","Width":"40%"},{"Val":"203","Width":"20%"},{"Val":"60","Width":"20%"},{"Val":"Yes","Width":"20%"}],[{"Val":"Adjunct 2","Width":"40%"},{"Val":"207","Width":"20%"},{"Val":"10","Width":"20%"},{"Val":"No","Width":"20%"}]]},{"Title":"Hops","Cols":[{"Val":"Ingredient","Width":"40%"},{"Val":"Amount(oz)","Width":"20%"},{"Val":"AA(%)","Width":"20%"},{"Val":"Time(mins)","Width":"20%"}],"Rows":[[{"Val":"Styrian Goldings","Width":"40%"},{"Val":"0.5","Width":"20%"},{"Val":"5.5","Width":"20%"},{"Val":"60","Width":"20%"}],[{"Val":"Loral","Width":"40%"},{"Val":"0.12","Width":"20%"},{"Val":"11.7","Width":"20%"},{"Val":"60","Width":"20%"}]]},{"Title":"Other Boil Ingredients","Cols":[{"Val":"Ingredient","Width":"40%"},{"Val":"Amount(oz)","Width":"20%"},{"Val":"Units","Width":"20%"},{"Val":"Time(mins)","Width":"20%"}],"Rows":[[{"Val":"Coriander Seed","Width":"40%"},{"Val":"0.2","Width":"20%"},{"Val":"oz","Width":"20%"},{"Val":"60","Width":"20%"}],[{"Val":"Orange Zest","Width":"40%"},{"Val":"2","Width":"20%"},{"Val":"oz","Width":"20%"},{"Val":"10","Width":"20%"}]]}]},{"Title":"FERMENTATION","Stats":[{"Item1":"Fermentation Type","Item2":"Ale"}],"Tables":[{"Title":"Yeast","Cols":[{"Val":"Name","Width":"40%"},{"Val":"Expected AA%","Width":"20%"},{"Val":"Range Temp(째F)","Width":"20%"},{"Val":"Pitch Temp(mins)","Width":"20%"}],"Rows":[[{"Val":"Fermentis SafAle S-04","Width":"40%"},{"Val":"80","Width":"20%"},{"Val":"59 - 68","Width":"20%"},{"Val":"63","Width":"20%"}]]},{"Title":"Fermentation Steps","Cols":[{"Val":"Step","Width":"40%"},{"Val":"Temp(째F)","Width":"20%"},{"Val":"Days","Width":"20%"},{"Val":"Hours","Width":"20%"}],"Rows":[[{"Val":"Fermentation","Width":"40%"},{"Val":"63","Width":"20%"},{"Val":"10","Width":"20%"},{"Val":"0","Width":"20%"}],[{"Val":"Crash Chill","Width":"40%"},{"Val":"44","Width":"20%"},{"Val":"0","Width":"20%"},{"Val":"0","Width":"20%"}]]}]}],"Stats":{"OG":"1.065","FG":"1.013","IBU":"24","SRM":"14","ABV":"7.1%"},"Style":"BJCP 2008 : 18.B Belgian Dubbel","SpecialBrewingInstructions":"","AverageRating":null,"NumRatings":0,"Reviews":[]},"OwnedByUser":false,"OwnedByPicoBrew":false,"CanAccess":true,"IsAdmin":false,"AdminView":false,"RedirectURL":null,"PicoBrew_ProfileID":0,"User_ProfileID":0,"UserRated":false,"UserCommented":false,"UserRating":null,"CompartmentNames":{"adjunct":{"0":"Pass Through","2":"Adjunct 1","3":"Adjunct 2","4":"Adjunct 3","5":"Adjunct 4"},"step":{"0":"Pass Through","2":"Adjunct 1","3":"Adjunct 2","4":"Adjunct 3","5":"Adjunct 4","1":"Mash","6":"Pause"}}}}