{"RecipeGUID":"3eaa338511974151922bfa8b2a042076","VM":{"Recipe":{"RecipeID":21057,"GUID":"3eaa338511974151922bfa8b2a042076","PreviousGUID":"2f408a6c930e4e1fa79cb1d8f8ac3b66","Efficiency":55.0,"Author":"Elusive Pastry","Name":"Monk Ale v0.1","WortSize":null,"BatchSize":2.5,"CreationDate":"2015-04-24T15:02:20.627","ABV":3.5,"IBU":27.0,"SRM":29.0,"FG":1.009,"OG":1.036,"Version":1,"StyleID":66,"BeerStyle":{"StyleID":66,"CatNumCode":"16","CatLettCode":"E","StyleNameCode":"Belgian Specialty Ale","MaxABV":8.0,"MaxSRM":8.0,"MaxIBU":40.0,"MaxFG":1.016,"MaxOG":1.07,"MinABV":4.0,"MinSRM":3.0,"MinIBU":20.0,"MinFG":1.008,"MinOG":1.04,"StyleGuide":"BJCP 2008"},"MashProfile":null,"Notes":"Steep – 2 ozs chocolate 4 ozs carapils 4 ozs crystal and water salts in 1.5  gallons of water at 154F for 30 minutes \nAdd 1 can of liquid malt extract.  8ozs of dry malt extract and 8 ozs of candy sugar \n add .5ozs of Styring Golding and .375 ozs of saaz hops.  Boil for 45 minutes\nadd irish moss.  Boil for 10 more minutes\nadd .12 ozs of Saaz hops.  Boil for 5 minutes.\nWhen wort is at ambient temperature pitch yeast.","SyncStatus":true,"H2O":3.29,"RecipeFile":null,"Locked":true,"Shared":true,"OriginalName":"Elusive test 1","OriginalAuthor":"Elusive Pastry on 4/18/2015","TastingNotes":"A brown, hoppy, light bodied Belgian Specialty Ale.","BoilSize":null,"Deleted":false,"Imported":false,"OriginalAuthorID":2906,"WhirlpoolTemp":null,"BoilTemp":207,"BoilTime":60,"MashTime":20,"MashTemp":154,"MashType":0,"IsFirstWort":false,"Errors":[],"Warnings":[{"Type":11,"Description":"WARNING: Your mash volume may be too low and may cause foaming.  We suggest increasing the batch size or increasing the amount of fermentables."}],"Fermentables":[{"Amount":3.3,"ColorPts":3.4374228308452124,"Errors":[],"PotentialGravity":23.04335816118709651557000,"FermentableID":118,"Name":"Munich LME","Color":8.0,"Yield":35.0,"FermentableType":"Extract"},{"Amount":0.5,"ColorPts":0.12369513974632393,"Errors":[],"PotentialGravity":4.3592846391509833997000,"FermentableID":117,"Name":"Light Dry Malt Extract","Color":1.9,"Yield":43.7,"FermentableType":"DryExtract"},{"Amount":0.25,"ColorPts":0.048827028847233139,"Errors":[],"PotentialGravity":1.651939442204579014622000,"FermentableID":70,"Name":"CaraPils","Color":1.5,"Yield":33.12,"FermentableType":"Grain"},{"Amount":0.125,"ColorPts":5.6964866988438656,"Errors":[],"PotentialGravity":0.82297707718525216127000,"FermentableID":74,"Name":"Chocolate","Color":350.0,"Yield":33.0,"FermentableType":"Grain"},{"Amount":0.25,"ColorPts":1.7903243910652149,"Errors":[],"PotentialGravity":1.673386723610013927916000,"FermentableID":48,"Name":"British Crystal 50-60L","Color":55.0,"Yield":33.55,"FermentableType":"Grain"},{"Amount":0.5,"ColorPts":17.903243910652151,"Errors":[],"PotentialGravity":4.44906395666210378093000,"FermentableID":28,"Name":"Belgian Candi Sugar Dark","Color":275.0,"Yield":44.6,"FermentableType":"Sugar"}],"Hops":[{"Location":2,"Amount":0.375,"IBU":8.539449,"Time":45.0,"BoilUse":0,"Errors":[],"AdjunctRound":1,"HopID":55,"Name":"Saaz","Alpha":3.5},{"Location":2,"Amount":0.5,"IBU":17.8921776,"Time":45.0,"BoilUse":0,"Errors":[],"AdjunctRound":1,"HopID":64,"Name":"Styrian Goldings","Alpha":5.5},{"Location":4,"Amount":0.12,"IBU":0.5936398,"Time":5.0,"BoilUse":4,"Errors":[],"AdjunctRound":1,"HopID":55,"Name":"Saaz","Alpha":3.5}],"DryHops":[],"WhirlpoolHops":[],"Adjuncts":[{"Location":3,"Amount":0.2,"Time":10,"Units":null,"BoilUse":0,"Errors":[],"AdjunctRound":1,"AdjunctID":17,"Name":"Irish Moss","Use":"Fining","AdjunctType":"Fining"}],"WhirlpoolAdjuncts":[],"DryAdjuncts":[],"Yeast":{"YeastID":119,"Name":"SafAle","Laboratory":"Fermentis","ProductID":"T-58","MinAtten":70.0,"MaxAtten":80.0,"MinTemp":59.0,"MaxTemp":68.0,"ExpectedAtten":75.0,"ExpectedTemp":63.0},"Amendments":[],"MachineSteps":[{"ID":21057,"Step":1,"Name":"Heat Water","Temperature":154,"Time":0,"Drain":0,"StepLocation":0},{"ID":21057,"Step":2,"Name":"Mash","Temperature":154,"Time":20,"Drain":8,"StepLocation":1},{"ID":21057,"Step":3,"Name":"Heat to Boil","Temperature":207,"Time":0,"Drain":0,"StepLocation":0},{"ID":21057,"Step":4,"Name":"Pre-Hop Boil","Temperature":207,"Time":15,"Drain":0,"StepLocation":0},{"ID":21057,"Step":5,"Name":"Boil Adjunct 1","Temperature":207,"Time":40,"Drain":0,"StepLocation":2},{"ID":21057,"Step":6,"Name":"Boil Adjunct 2","Temperature":207,"Time":5,"Drain":5,"StepLocation":3},{"ID":21057,"Step":7,"Name":"Connect Chiller","Temperature":0,"Time":0,"Drain":0,"StepLocation":6},{"ID":21057,"Step":8,"Name":"Chill","Temperature":63,"Time":10,"Drain":10,"StepLocation":0}],"FermentationSteps":[{"Step":1,"Name":"Fermentation","Temp":63.0,"Days":10.0,"Hours":0.0,"Minutes":0},{"Step":2,"Name":"Crash Chill","Temp":44.0,"Days":0.0,"Hours":0.0,"Minutes":0}],"FermentationType":0,"BoilSteps":[{"Name":"Pass Through","Temp":207,"Time":60,"BoilTime":0,"Ramp":true,"IsWhirlpool":false,"AdjunctRound":1,"Location":0,"Errors":[]},{"Name":"Adjunct 1","Temp":207,"Time":45,"BoilTime":40,"Ramp":false,"IsWhirlpool":false,"AdjunctRound":1,"Location":2,"Errors":[]},{"Name":"Adjunct 2","Temp":207,"Time":10,"BoilTime":10,"Ramp":false,"IsWhirlpool":false,"AdjunctRound":1,"Location":3,"Errors":[]},{"Name":"Adjunct 3","Temp":207,"Time":5,"BoilTime":5,"Ramp":false,"IsWhirlpool":false,"AdjunctRound":1,"Location":4,"Errors":[]}],"MashSteps":[{"Name":"Single Step Infusion Mash","Temp":154.0,"Time":20.0,"Style":"Infusion","Errors":[]}],"WhirlpoolSteps":[],"IsMetric":false,"SessionCount":0,"CrafterVersion":1,"IsBiB":false,"RecipeType":0,"HumanBrewingSteps":{"FillKeg":"Fill keg with 3.29 Gal water","LoadWaterAmendments":"Load selected water amendments (generally dry ingredients go in with milled grain, liquid ingredients in start water, your recipe may vary)","LoadMash":"Mill grain and load into mash compartment","LoadAdjuncts":"Load hops and other boil/whirlpool additions into adjunct compartments:","LoadFermentationAdditions":"Load dry hops and fermentation additions into fermentation keg:","Mash":[{"Name":"Munich LME","Units":"lbs","Amount":3.3},{"Name":"Light Dry Malt Extract","Units":"lbs","Amount":0.5},{"Name":"CaraPils","Units":"lbs","Amount":0.25},{"Name":"Chocolate","Units":"lbs","Amount":0.125},{"Name":"British Crystal 50-60L","Units":"lbs","Amount":0.25},{"Name":"Belgian Candi Sugar Dark","Units":"lbs","Amount":0.5}],"FermentationAdditions":[],"AdjunctRounds":[{"Round":1,"AddInTime":0,"Adjuncts1":[{"Name":"Saaz","Units":"oz","Amount":0.375},{"Name":"Styrian Goldings","Units":"oz","Amount":0.5}],"Adjuncts2":[{"Name":"Irish Moss","Units":"oz","Amount":0.2}],"Adjuncts3":[{"Name":"Saaz","Units":"oz","Amount":0.12}],"Adjuncts4":[]}],"IsMetric":false,"TotalRounds":1},"ZKit":false},"Content":{"Sections":[{"Title":"WATER","Stats":[{"Item1":"Starting Water","Item2":"3.29 gal Water (27.44 lbs)"},{"Item1":"Batch Size","Item2":"2.5 Gal"}],"Tables":[]},{"Title":"MASH","Stats":[{"Item1":"Mash Type","Item2":"Single Step Infusion"}],"Tables":[{"Title":"Mash Steps","Cols":[{"Val":"Step","Width":"40%"},{"Val":"Temp(°F)","Width":"20%"},{"Val":"Time(mins)","Width":"20%"},{"Val":"","Width":"20%"}],"Rows":[[{"Val":"Single Step Infusion Mash","Width":"40%"},{"Val":"154","Width":"20%"},{"Val":"20","Width":"20%"},{"Val":"","Width":"20%"}]]},{"Title":"Fermentables","Cols":[{"Val":"Ingredient","Width":"40%"},{"Val":"Amount(lbs)","Width":"20%"},{"Val":"Gravity(pts)","Width":"20%"},{"Val":"Color(pts)","Width":"20%"}],"Rows":[[{"Val":"Munich LME","Width":"40%"},{"Val":"3.3","Width":"20%"},{"Val":"1.035","Width":"20%"},{"Val":"3.44","Width":"20%"}],[{"Val":"Light Dry Malt Extract","Width":"40%"},{"Val":"0.5","Width":"20%"},{"Val":"1.044","Width":"20%"},{"Val":"0.12","Width":"20%"}],[{"Val":"CaraPils","Width":"40%"},{"Val":"0.25","Width":"20%"},{"Val":"1.033","Width":"20%"},{"Val":"0.05","Width":"20%"}],[{"Val":"Chocolate","Width":"40%"},{"Val":"0.125","Width":"20%"},{"Val":"1.033","Width":"20%"},{"Val":"5.70","Width":"20%"}],[{"Val":"British Crystal 50-60L","Width":"40%"},{"Val":"0.25","Width":"20%"},{"Val":"1.034","Width":"20%"},{"Val":"1.79","Width":"20%"}],[{"Val":"Belgian Candi Sugar Dark","Width":"40%"},{"Val":"0.5","Width":"20%"},{"Val":"1.045","Width":"20%"},{"Val":"17.90","Width":"20%"}]]}]},{"Title":"BOIL","Stats":[{"Item1":"Boil Time(mins)","Item2":"60"}],"Tables":[{"Title":"Boil Steps","Cols":[{"Val":"Step","Width":"40%"},{"Val":"Temp(°F)","Width":"20%"},{"Val":"Time(mins)","Width":"20%"},{"Val":"Ramp","Width":"20%"}],"Rows":[[{"Val":"Pass Through","Width":"40%"},{"Val":"207","Width":"20%"},{"Val":"60","Width":"20%"},{"Val":"Yes","Width":"20%"}],[{"Val":"Adjunct 1","Width":"40%"},{"Val":"207","Width":"20%"},{"Val":"45","Width":"20%"},{"Val":"No","Width":"20%"}],[{"Val":"Adjunct 2","Width":"40%"},{"Val":"207","Width":"20%"},{"Val":"10","Width":"20%"},{"Val":"No","Width":"20%"}],[{"Val":"Adjunct 3","Width":"40%"},{"Val":"207","Width":"20%"},{"Val":"5","Width":"20%"},{"Val":"No","Width":"20%"}]]},{"Title":"Hops","Cols":[{"Val":"Ingredient","Width":"40%"},{"Val":"Amount(oz)","Width":"20%"},{"Val":"AA(%)","Width":"20%"},{"Val":"Time(mins)","Width":"20%"}],"Rows":[[{"Val":"Saaz","Width":"40%"},{"Val":"0.375","Width":"20%"},{"Val":"3.5","Width":"20%"},{"Val":"45","Width":"20%"}],[{"Val":"Styrian Goldings","Width":"40%"},{"Val":"0.5","Width":"20%"},{"Val":"5.5","Width":"20%"},{"Val":"45","Width":"20%"}],[{"Val":"Saaz","Width":"40%"},{"Val":"0.12","Width":"20%"},{"Val":"3.5","Width":"20%"},{"Val":"5","Width":"20%"}]]},{"Title":"Other Boil Ingredients","Cols":[{"Val":"Ingredient","Width":"40%"},{"Val":"Amount(oz)","Width":"20%"},{"Val":"Units","Width":"20%"},{"Val":"Time(mins)","Width":"20%"}],"Rows":[[{"Val":"Irish Moss","Width":"40%"},{"Val":"0.2","Width":"20%"},{"Val":"oz","Width":"20%"},{"Val":"10","Width":"20%"}]]}]},{"Title":"FERMENTATION","Stats":[{"Item1":"Fermentation Type","Item2":"Ale"}],"Tables":[{"Title":"Yeast","Cols":[{"Val":"Name","Width":"40%"},{"Val":"Expected AA%","Width":"20%"},{"Val":"Range Temp(°F)","Width":"20%"},{"Val":"Pitch Temp(mins)","Width":"20%"}],"Rows":[[{"Val":"Fermentis SafAle T-58","Width":"40%"},{"Val":"75","Width":"20%"},{"Val":"59 - 68","Width":"20%"},{"Val":"63","Width":"20%"}]]},{"Title":"Fermentation Steps","Cols":[{"Val":"Step","Width":"40%"},{"Val":"Temp(°F)","Width":"20%"},{"Val":"Days","Width":"20%"},{"Val":"Hours","Width":"20%"}],"Rows":[[{"Val":"Fermentation","Width":"40%"},{"Val":"63","Width":"20%"},{"Val":"10","Width":"20%"},{"Val":"0","Width":"20%"}],[{"Val":"Crash Chill","Width":"40%"},{"Val":"44","Width":"20%"},{"Val":"0","Width":"20%"},{"Val":"0","Width":"20%"}]]}]}],"Stats":{"OG":"1.036","FG":"1.009","IBU":"27","SRM":"29","ABV":"3.5%"},"Style":"BJCP 2008 : 16.E Belgian Specialty Ale","SpecialBrewingInstructions":"Steep – 2 ozs chocolate 4 ozs carapils 4 ozs crystal and water salts in 1.5  gallons of water at 154F for 30 minutes \nAdd 1 can of liquid malt extract.  8ozs of dry malt extract and 8 ozs of candy sugar \n add .5ozs of Styring Golding and .375 ozs of saaz hops.  Boil for 45 minutes\nadd irish moss.  Boil for 10 more minutes\nadd .12 ozs of Saaz hops.  Boil for 5 minutes.\nWhen wort is at ambient temperature pitch yeast.","AverageRating":null,"NumRatings":0,"Reviews":[]},"OwnedByUser":false,"OwnedByPicoBrew":false,"CanAccess":true,"IsAdmin":false,"AdminView":false,"RedirectURL":null,"PicoBrew_ProfileID":0,"User_ProfileID":0,"UserRated":false,"UserCommented":false,"UserRating":null,"CompartmentNames":{"adjunct":{"0":"Pass Through","2":"Adjunct 1","3":"Adjunct 2","4":"Adjunct 3","5":"Adjunct 4"},"step":{"0":"Pass Through","2":"Adjunct 1","3":"Adjunct 2","4":"Adjunct 3","5":"Adjunct 4","1":"Mash","6":"Pause"}}}}