{"RecipeGUID":"4e9b0ec62b284ffaa3e1e9accea42900","VM":{"Recipe":{"RecipeID":34158,"GUID":"4e9b0ec62b284ffaa3e1e9accea42900","PreviousGUID":"1b913e3dbdeb45f49994c5438f654de4","Efficiency":55.0,"Author":"Marc Bocklet","Name":"Rice Lager v2","WortSize":null,"BatchSize":2.5,"CreationDate":"2015-09-13T19:21:24.533","ABV":6.2,"IBU":21.0,"SRM":3.0,"FG":1.0059,"OG":1.0537,"Version":1,"StyleID":87,"BeerStyle":{"StyleID":87,"CatNumCode":"23","CatLettCode":"A","StyleNameCode":"Specialty Beer","MaxABV":0.0,"MaxSRM":0.0,"MaxIBU":0.0,"MaxFG":0.0,"MaxOG":0.0,"MinABV":0.0,"MinSRM":0.0,"MinIBU":0.0,"MinFG":0.0,"MinOG":0.0,"StyleGuide":"BJCP 2008"},"MashProfile":null,"Notes":"You can substitute S-189 with Saflager S-23, but there is a chance that the beer will turn out more estery - which may not be desired.\nDon't forget to preboil the basmati - we cooked it for about 15 minutes before adding it to the mash.","SyncStatus":true,"H2O":3.5,"RecipeFile":null,"Locked":true,"Shared":true,"OriginalName":"Kirin Clone v1","OriginalAuthor":"Marc Bocklet on 5/24/2015","TastingNotes":"A very pale, balanced, medium-bodied Specialty Beer.","BoilSize":null,"Deleted":false,"Imported":true,"OriginalAuthorID":2781,"WhirlpoolTemp":null,"BoilTemp":207,"BoilTime":60,"MashTime":90,"MashTemp":152,"MashType":0,"IsFirstWort":false,"Errors":[],"Warnings":[],"Fermentables":[{"Amount":2.1652129856121016,"ColorPts":0.45155788523943519,"Errors":[],"PotentialGravity":17.45850410735445337701000,"FermentableID":97,"Name":"Flaked Rice","Color":0.55,"Yield":39.6,"FermentableType":"OtherGrain"},{"Amount":3.2478194784181524,"ColorPts":2.0320104835774586,"Errors":[],"PotentialGravity":24.91474023653710184739000,"FermentableID":108,"Name":"German Pilsener","Color":1.65,"Yield":37.675,"FermentableType":"Grain"},{"Amount":0.54130324640302541,"ColorPts":0.3078803762996149,"Errors":[],"PotentialGravity":3.650414495174114443374000,"FermentableID":70,"Name":"CaraPils","Color":1.5,"Yield":33.12,"FermentableType":"Grain"},{"Amount":1.0,"ColorPts":0.20855125488349161,"Errors":[],"PotentialGravity":7.67631116093434107222000,"FermentableID":24,"Name":"Basmati Rice","Color":0.55,"Yield":37.7,"FermentableType":"OtherGrain"}],"Hops":[{"Location":2,"Amount":0.4,"IBU":8.462711,"Time":60.0,"BoilUse":0,"Errors":[],"AdjunctRound":1,"HopID":55,"Name":"Saaz","Alpha":3.5},{"Location":2,"Amount":0.3,"IBU":9.067191,"Time":60.0,"BoilUse":0,"Errors":[],"AdjunctRound":1,"HopID":38,"Name":"Mount Hood","Alpha":5.0},{"Location":3,"Amount":0.1,"IBU":1.05013072,"Time":15.0,"BoilUse":0,"Errors":[],"AdjunctRound":1,"HopID":55,"Name":"Saaz","Alpha":3.5},{"Location":3,"Amount":0.1,"IBU":1.5001868,"Time":15.0,"BoilUse":0,"Errors":[],"AdjunctRound":1,"HopID":38,"Name":"Mount Hood","Alpha":5.0},{"Location":4,"Amount":0.1,"IBU":0.568456948,"Time":7.0,"BoilUse":0,"Errors":[],"AdjunctRound":1,"HopID":55,"Name":"Saaz","Alpha":3.5},{"Location":4,"Amount":0.1,"IBU":0.812081337,"Time":7.0,"BoilUse":0,"Errors":[],"AdjunctRound":1,"HopID":38,"Name":"Mount Hood","Alpha":5.0}],"DryHops":[],"WhirlpoolHops":[],"Adjuncts":[],"WhirlpoolAdjuncts":[],"DryAdjuncts":[],"Yeast":{"YeastID":117,"Name":"SafLager","Laboratory":"Fermentis","ProductID":"S-189","MinAtten":80.0,"MaxAtten":88.0,"MinTemp":53.0,"MaxTemp":59.0,"ExpectedAtten":89.0,"ExpectedTemp":56.0},"Amendments":[],"MachineSteps":[{"ID":34158,"Step":1,"Name":"Heat Water","Temperature":152,"Time":0,"Drain":0,"StepLocation":0},{"ID":34158,"Step":2,"Name":"Mash","Temperature":152,"Time":90,"Drain":8,"StepLocation":1},{"ID":34158,"Step":3,"Name":"Heat to Boil","Temperature":207,"Time":0,"Drain":0,"StepLocation":0},{"ID":34158,"Step":4,"Name":"Boil Adjunct 1","Temperature":207,"Time":45,"Drain":0,"StepLocation":2},{"ID":34158,"Step":5,"Name":"Boil Adjunct 2","Temperature":207,"Time":8,"Drain":0,"StepLocation":3},{"ID":34158,"Step":6,"Name":"Boil Adjunct 3","Temperature":207,"Time":7,"Drain":5,"StepLocation":4},{"ID":34158,"Step":7,"Name":"Connect Chiller","Temperature":0,"Time":0,"Drain":0,"StepLocation":6},{"ID":34158,"Step":8,"Name":"Chill","Temperature":56,"Time":10,"Drain":10,"StepLocation":0}],"FermentationSteps":[{"Step":1,"Name":"Primary Fermentation","Temp":56.0,"Days":21.0,"Hours":0.0,"Minutes":0},{"Step":2,"Name":"Lagering","Temp":35.0,"Days":28.0,"Hours":0.0,"Minutes":0}],"FermentationType":1,"BoilSteps":[{"Name":"Adjunct 1","Temp":207,"Time":60,"BoilTime":45,"Ramp":true,"IsWhirlpool":false,"AdjunctRound":1,"Location":2,"Errors":[]},{"Name":"Adjunct 2","Temp":207,"Time":15,"BoilTime":8,"Ramp":false,"IsWhirlpool":false,"AdjunctRound":1,"Location":3,"Errors":[]},{"Name":"Adjunct 3","Temp":207,"Time":7,"BoilTime":7,"Ramp":false,"IsWhirlpool":false,"AdjunctRound":1,"Location":4,"Errors":[]}],"MashSteps":[{"Name":"Single Step Infusion Mash","Temp":152.0,"Time":90.0,"Style":"Infusion","Errors":[]}],"WhirlpoolSteps":[],"IsMetric":false,"SessionCount":0,"CrafterVersion":1,"IsBiB":false,"RecipeType":0,"HumanBrewingSteps":{"FillKeg":"Fill keg with 3.50 Gal water","LoadWaterAmendments":"Load selected water amendments (generally dry ingredients go in with milled grain, liquid ingredients in start water, your recipe may vary)","LoadMash":"Mill grain and load into mash compartment","LoadAdjuncts":"Load hops and other boil/whirlpool additions into adjunct compartments:","LoadFermentationAdditions":"Load dry hops and fermentation additions into fermentation keg:","Mash":[{"Name":"Flaked Rice","Units":"lbs","Amount":2.1652129856121016},{"Name":"German Pilsener","Units":"lbs","Amount":3.2478194784181524},{"Name":"CaraPils","Units":"lbs","Amount":0.54130324640302541},{"Name":"Basmati Rice","Units":"lbs","Amount":1.0}],"FermentationAdditions":[],"AdjunctRounds":[{"Round":1,"AddInTime":0,"Adjuncts1":[{"Name":"Saaz","Units":"oz","Amount":0.4},{"Name":"Mount Hood","Units":"oz","Amount":0.3}],"Adjuncts2":[{"Name":"Saaz","Units":"oz","Amount":0.1},{"Name":"Mount Hood","Units":"oz","Amount":0.1}],"Adjuncts3":[{"Name":"Saaz","Units":"oz","Amount":0.1},{"Name":"Mount Hood","Units":"oz","Amount":0.1}],"Adjuncts4":[]}],"IsMetric":false,"TotalRounds":1},"ZKit":false},"Content":{"Sections":[{"Title":"WATER","Stats":[{"Item1":"Starting Water","Item2":"3.5 gal Water (29.19 lbs)"},{"Item1":"Batch Size","Item2":"2.5 Gal"}],"Tables":[]},{"Title":"MASH","Stats":[{"Item1":"Mash Type","Item2":"Single Step Infusion"}],"Tables":[{"Title":"Mash Steps","Cols":[{"Val":"Step","Width":"40%"},{"Val":"Temp(째F)","Width":"20%"},{"Val":"Time(mins)","Width":"20%"},{"Val":"","Width":"20%"}],"Rows":[[{"Val":"Single Step Infusion Mash","Width":"40%"},{"Val":"152","Width":"20%"},{"Val":"90","Width":"20%"},{"Val":"","Width":"20%"}]]},{"Title":"Fermentables","Cols":[{"Val":"Ingredient","Width":"40%"},{"Val":"Amount(lbs)","Width":"20%"},{"Val":"Gravity(pts)","Width":"20%"},{"Val":"Color(pts)","Width":"20%"}],"Rows":[[{"Val":"Flaked Rice","Width":"40%"},{"Val":"2.1652129856121","Width":"20%"},{"Val":"1.04","Width":"20%"},{"Val":"0.45","Width":"20%"}],[{"Val":"German Pilsener","Width":"40%"},{"Val":"3.24781947841815","Width":"20%"},{"Val":"1.038","Width":"20%"},{"Val":"2.03","Width":"20%"}],[{"Val":"CaraPils","Width":"40%"},{"Val":"0.541303246403025","Width":"20%"},{"Val":"1.033","Width":"20%"},{"Val":"0.31","Width":"20%"}],[{"Val":"Basmati Rice","Width":"40%"},{"Val":"1","Width":"20%"},{"Val":"1.038","Width":"20%"},{"Val":"0.21","Width":"20%"}]]}]},{"Title":"BOIL","Stats":[{"Item1":"Boil Time(mins)","Item2":"60"}],"Tables":[{"Title":"Boil Steps","Cols":[{"Val":"Step","Width":"40%"},{"Val":"Temp(째F)","Width":"20%"},{"Val":"Time(mins)","Width":"20%"},{"Val":"Ramp","Width":"20%"}],"Rows":[[{"Val":"Adjunct 1","Width":"40%"},{"Val":"207","Width":"20%"},{"Val":"60","Width":"20%"},{"Val":"Yes","Width":"20%"}],[{"Val":"Adjunct 2","Width":"40%"},{"Val":"207","Width":"20%"},{"Val":"15","Width":"20%"},{"Val":"No","Width":"20%"}],[{"Val":"Adjunct 3","Width":"40%"},{"Val":"207","Width":"20%"},{"Val":"7","Width":"20%"},{"Val":"No","Width":"20%"}]]},{"Title":"Hops","Cols":[{"Val":"Ingredient","Width":"40%"},{"Val":"Amount(oz)","Width":"20%"},{"Val":"AA(%)","Width":"20%"},{"Val":"Time(mins)","Width":"20%"}],"Rows":[[{"Val":"Saaz","Width":"40%"},{"Val":"0.4","Width":"20%"},{"Val":"3.5","Width":"20%"},{"Val":"60","Width":"20%"}],[{"Val":"Mount Hood","Width":"40%"},{"Val":"0.3","Width":"20%"},{"Val":"5","Width":"20%"},{"Val":"60","Width":"20%"}],[{"Val":"Saaz","Width":"40%"},{"Val":"0.1","Width":"20%"},{"Val":"3.5","Width":"20%"},{"Val":"15","Width":"20%"}],[{"Val":"Mount Hood","Width":"40%"},{"Val":"0.1","Width":"20%"},{"Val":"5","Width":"20%"},{"Val":"15","Width":"20%"}],[{"Val":"Saaz","Width":"40%"},{"Val":"0.1","Width":"20%"},{"Val":"3.5","Width":"20%"},{"Val":"7","Width":"20%"}],[{"Val":"Mount Hood","Width":"40%"},{"Val":"0.1","Width":"20%"},{"Val":"5","Width":"20%"},{"Val":"7","Width":"20%"}]]}]},{"Title":"FERMENTATION","Stats":[{"Item1":"Fermentation Type","Item2":"Lager"}],"Tables":[{"Title":"Yeast","Cols":[{"Val":"Name","Width":"40%"},{"Val":"Expected AA%","Width":"20%"},{"Val":"Range Temp(째F)","Width":"20%"},{"Val":"Pitch Temp(mins)","Width":"20%"}],"Rows":[[{"Val":"Fermentis SafLager S-189","Width":"40%"},{"Val":"89","Width":"20%"},{"Val":"53 - 59","Width":"20%"},{"Val":"56","Width":"20%"}]]},{"Title":"Fermentation Steps","Cols":[{"Val":"Step","Width":"40%"},{"Val":"Temp(째F)","Width":"20%"},{"Val":"Days","Width":"20%"},{"Val":"Hours","Width":"20%"}],"Rows":[[{"Val":"Primary Fermentation","Width":"40%"},{"Val":"56","Width":"20%"},{"Val":"21","Width":"20%"},{"Val":"0","Width":"20%"}],[{"Val":"Lagering","Width":"40%"},{"Val":"35","Width":"20%"},{"Val":"28","Width":"20%"},{"Val":"0","Width":"20%"}]]}]}],"Stats":{"OG":"1.054","FG":"1.006","IBU":"21","SRM":"3","ABV":"6.2%"},"Style":"BJCP 2008 : 23.A Specialty Beer","SpecialBrewingInstructions":"You can substitute S-189 with Saflager S-23, but there is a chance that the beer will turn out more estery - which may not be desired.\nDon't forget to preboil the basmati - we cooked it for about 15 minutes before adding it to the mash.","AverageRating":null,"NumRatings":0,"Reviews":[{"Date":"9/13/2015","Content":"Brewed on 13/06/2015. First bottle tested on 13/09/2015. Dry taste with some residual sweetness. Unfortunately, we used S-23, which imparted a hint of fruit. Taste is still good, in our opinion, but next time we'll use a cleaner lager yeast (recipe is already changed to S-189). Alternatively, use a clean liquid lager yeast of your choice.","Username":"sheep2045"}]},"OwnedByUser":false,"OwnedByPicoBrew":false,"CanAccess":true,"IsAdmin":false,"AdminView":false,"RedirectURL":null,"PicoBrew_ProfileID":0,"User_ProfileID":0,"UserRated":false,"UserCommented":false,"UserRating":null,"CompartmentNames":{"adjunct":{"0":"Pass Through","2":"Adjunct 1","3":"Adjunct 2","4":"Adjunct 3","5":"Adjunct 4"},"step":{"0":"Pass Through","2":"Adjunct 1","3":"Adjunct 2","4":"Adjunct 3","5":"Adjunct 4","1":"Mash","6":"Pause"}}}}