{"RecipeGUID":"bcb326143f904f1e9a7141c5668bd0c4","VM":{"Recipe":{"RecipeID":22389,"GUID":"bcb326143f904f1e9a7141c5668bd0c4","PreviousGUID":"00000000000000000000000000000000","Efficiency":70.0,"Author":"Mark Guidarelli","Name":"Kwe-Kwak v1","WortSize":null,"BatchSize":2.5,"CreationDate":"2015-05-10T02:37:27.633","ABV":8.6,"IBU":24.0,"SRM":13.0,"FG":1.022,"OG":1.088,"Version":1,"StyleID":77,"BeerStyle":{"StyleID":77,"CatNumCode":"18","CatLettCode":"E","StyleNameCode":"Belgian Dark Strong Ale","MaxABV":11.0,"MaxSRM":22.0,"MaxIBU":35.0,"MaxFG":1.024,"MaxOG":1.11,"MinABV":8.0,"MinSRM":12.0,"MinIBU":20.0,"MinFG":1.01,"MinOG":1.075,"StyleGuide":"BJCP 2008"},"MashProfile":null,"Notes":"Place 1/3 tablet of Whirfloc into third hops cage (10 minutes of boil).\nAdd Belgian Candi Sugar into keg at 40 minute point of first hops (20 minutes of boil).","SyncStatus":true,"H2O":3.35,"RecipeFile":null,"Locked":true,"Shared":true,"OriginalName":"Qwee-Qway","OriginalAuthor":"Mark Guidarelli on 3/3/2015","TastingNotes":"An amber, very sweet, Belgian Dark Strong Ale.","BoilSize":null,"Deleted":false,"Imported":false,"OriginalAuthorID":2118,"WhirlpoolTemp":null,"BoilTemp":207,"BoilTime":60,"MashTime":90,"MashTemp":152,"MashType":2,"IsFirstWort":false,"Errors":[],"Warnings":[],"Fermentables":[{"Amount":6.5,"ColorPts":3.8613861386138613,"Errors":[],"PotentialGravity":61.2785805936072778082000,"FermentableID":39,"Name":"Belgian Two-row Pale","Color":3.0,"Yield":36.6,"FermentableType":"Grain"},{"Amount":1.5,"ColorPts":2.3762376237623761,"Errors":[],"PotentialGravity":14.14121090621707087882000,"FermentableID":107,"Name":"German Munich","Color":8.0,"Yield":36.6,"FermentableType":"Grain"},{"Amount":0.15,"ColorPts":6.564356435643564,"Errors":[],"PotentialGravity":1.105023584474887934248000,"FermentableID":38,"Name":"Belgian Special B","Color":221.0,"Yield":28.6,"FermentableType":"Grain"},{"Amount":1.0,"ColorPts":0.198019801980198,"Errors":[],"PotentialGravity":11.47524491570074577872000,"FermentableID":140,"Name":"Belgian Candi Sugar Clear","Color":1.0,"Yield":44.55,"FermentableType":"Sugar"}],"Hops":[{"Location":2,"Amount":0.5,"IBU":15.9884987,"Time":60.0,"BoilUse":0,"Errors":[],"AdjunctRound":1,"HopID":11,"Name":"Challenger","Alpha":7.2},{"Location":3,"Amount":0.5,"IBU":5.78666449,"Time":15.0,"BoilUse":0,"Errors":[],"AdjunctRound":1,"HopID":64,"Name":"Styrian Goldings","Alpha":5.25},{"Location":4,"Amount":0.001,"IBU":1.61085541E-06,"Time":10.0,"BoilUse":0,"Errors":[],"AdjunctRound":1,"HopID":82,"Name":"Other (See Notes)","Alpha":0.001},{"Location":5,"Amount":0.25,"IBU":0.775034249,"Time":5.0,"BoilUse":0,"Errors":[],"AdjunctRound":1,"HopID":55,"Name":"Saaz","Alpha":3.5},{"Location":5,"Amount":0.25,"IBU":1.59435618,"Time":5.0,"BoilUse":0,"Errors":[],"AdjunctRound":1,"HopID":11,"Name":"Challenger","Alpha":7.2}],"DryHops":[],"WhirlpoolHops":[],"Adjuncts":[],"WhirlpoolAdjuncts":[],"DryAdjuncts":[],"Yeast":{"YeastID":32,"Name":"Belgian Abbey II","Laboratory":"Wyeast","ProductID":"1762","MinAtten":73.0,"MaxAtten":77.0,"MinTemp":65.0,"MaxTemp":75.0,"ExpectedAtten":75.0,"ExpectedTemp":70.0},"Amendments":[],"MachineSteps":[{"ID":22389,"Step":1,"Name":"Heat to Temp","Temperature":102,"Time":0,"Drain":0,"StepLocation":0},{"ID":22389,"Step":2,"Name":"Dough In","Temperature":102,"Time":20,"Drain":8,"StepLocation":1},{"ID":22389,"Step":3,"Name":"Heat to Mash","Temperature":152,"Time":0,"Drain":0,"StepLocation":0},{"ID":22389,"Step":4,"Name":"Mash 1","Temperature":152,"Time":30,"Drain":8,"StepLocation":1},{"ID":22389,"Step":5,"Name":"Mash 2","Temperature":154,"Time":60,"Drain":8,"StepLocation":1},{"ID":22389,"Step":6,"Name":"Heat to MO","Temperature":175,"Time":0,"Drain":0,"StepLocation":0},{"ID":22389,"Step":7,"Name":"Mash Out","Temperature":175,"Time":10,"Drain":10,"StepLocation":1},{"ID":22389,"Step":8,"Name":"Heat to Boil","Temperature":207,"Time":0,"Drain":0,"StepLocation":0},{"ID":22389,"Step":9,"Name":"Boil Adjunct 1","Temperature":207,"Time":45,"Drain":0,"StepLocation":2},{"ID":22389,"Step":10,"Name":"Boil Adjunct 2","Temperature":207,"Time":5,"Drain":0,"StepLocation":3},{"ID":22389,"Step":11,"Name":"Boil Adjunct 3","Temperature":207,"Time":5,"Drain":0,"StepLocation":4},{"ID":22389,"Step":12,"Name":"Boil Adjunct 4","Temperature":207,"Time":5,"Drain":5,"StepLocation":5},{"ID":22389,"Step":13,"Name":"Connect Chiller","Temperature":0,"Time":0,"Drain":0,"StepLocation":6},{"ID":22389,"Step":14,"Name":"Chill","Temperature":70,"Time":10,"Drain":10,"StepLocation":0}],"FermentationSteps":[{"Step":1,"Name":"Fermentation","Temp":70.0,"Days":10.0,"Hours":0.0,"Minutes":0},{"Step":2,"Name":"Crash Chill","Temp":44.0,"Days":0.0,"Hours":0.0,"Minutes":0}],"FermentationType":0,"BoilSteps":[{"Name":"Adjunct 1","Temp":207,"Time":60,"BoilTime":45,"Ramp":true,"IsWhirlpool":false,"AdjunctRound":1,"Location":2,"Errors":[]},{"Name":"Adjunct 2","Temp":207,"Time":15,"BoilTime":5,"Ramp":false,"IsWhirlpool":false,"AdjunctRound":1,"Location":3,"Errors":[]},{"Name":"Adjunct 3","Temp":207,"Time":10,"BoilTime":5,"Ramp":false,"IsWhirlpool":false,"AdjunctRound":1,"Location":4,"Errors":[]},{"Name":"Adjunct 4","Temp":207,"Time":5,"BoilTime":5,"Ramp":false,"IsWhirlpool":false,"AdjunctRound":1,"Location":5,"Errors":[]}],"MashSteps":[{"Name":"Dough In","Temp":102.0,"Time":20.0,"Style":"Infusion","Errors":[]},{"Name":"Mash 1","Temp":152.0,"Time":30.0,"Style":"Infusion","Errors":[]},{"Name":"Mash 2","Temp":154.0,"Time":60.0,"Style":"Infusion","Errors":[]},{"Name":"Mash Out","Temp":175.0,"Time":10.0,"Style":"Infusion","Errors":[]}],"WhirlpoolSteps":[],"IsMetric":false,"SessionCount":0,"CrafterVersion":1,"IsBiB":false,"RecipeType":0,"HumanBrewingSteps":{"FillKeg":"Fill keg with 3.35 Gal water","LoadWaterAmendments":"Load selected water amendments (generally dry ingredients go in with milled grain, liquid ingredients in start water, your recipe may vary)","LoadMash":"Mill grain and load into mash compartment","LoadAdjuncts":"Load hops and other boil/whirlpool additions into adjunct compartments:","LoadFermentationAdditions":"Load dry hops and fermentation additions into fermentation keg:","Mash":[{"Name":"Belgian Two-row Pale","Units":"lbs","Amount":6.5},{"Name":"German Munich","Units":"lbs","Amount":1.5},{"Name":"Belgian Special B","Units":"lbs","Amount":0.15},{"Name":"Belgian Candi Sugar Clear","Units":"lbs","Amount":1.0}],"FermentationAdditions":[],"AdjunctRounds":[{"Round":1,"AddInTime":0,"Adjuncts1":[{"Name":"Challenger","Units":"oz","Amount":0.5}],"Adjuncts2":[{"Name":"Styrian Goldings","Units":"oz","Amount":0.5}],"Adjuncts3":[{"Name":"Other (See Notes)","Units":"oz","Amount":0.001}],"Adjuncts4":[{"Name":"Saaz","Units":"oz","Amount":0.25},{"Name":"Challenger","Units":"oz","Amount":0.25}]}],"IsMetric":false,"TotalRounds":1},"ZKit":false},"Content":{"Sections":[{"Title":"WATER","Stats":[{"Item1":"Starting Water","Item2":"3.35 gal Water (27.94 lbs)"},{"Item1":"Batch Size","Item2":"2.5 Gal"}],"Tables":[]},{"Title":"MASH","Stats":[{"Item1":"Mash Type","Item2":"Custom"}],"Tables":[{"Title":"Mash Steps","Cols":[{"Val":"Step","Width":"40%"},{"Val":"Temp(째F)","Width":"20%"},{"Val":"Time(mins)","Width":"20%"},{"Val":"","Width":"20%"}],"Rows":[[{"Val":"Dough In","Width":"40%"},{"Val":"102","Width":"20%"},{"Val":"20","Width":"20%"},{"Val":"","Width":"20%"}],[{"Val":"Mash 1","Width":"40%"},{"Val":"152","Width":"20%"},{"Val":"30","Width":"20%"},{"Val":"","Width":"20%"}],[{"Val":"Mash 2","Width":"40%"},{"Val":"154","Width":"20%"},{"Val":"60","Width":"20%"},{"Val":"","Width":"20%"}],[{"Val":"Mash Out","Width":"40%"},{"Val":"175","Width":"20%"},{"Val":"10","Width":"20%"},{"Val":"","Width":"20%"}]]},{"Title":"Fermentables","Cols":[{"Val":"Ingredient","Width":"40%"},{"Val":"Amount(lbs)","Width":"20%"},{"Val":"Gravity(pts)","Width":"20%"},{"Val":"Color(pts)","Width":"20%"}],"Rows":[[{"Val":"Belgian Two-row Pale","Width":"40%"},{"Val":"6.5","Width":"20%"},{"Val":"1.037","Width":"20%"},{"Val":"3.86","Width":"20%"}],[{"Val":"German Munich","Width":"40%"},{"Val":"1.5","Width":"20%"},{"Val":"1.037","Width":"20%"},{"Val":"2.38","Width":"20%"}],[{"Val":"Belgian Special B","Width":"40%"},{"Val":"0.15","Width":"20%"},{"Val":"1.029","Width":"20%"},{"Val":"6.56","Width":"20%"}],[{"Val":"Belgian Candi Sugar Clear","Width":"40%"},{"Val":"1","Width":"20%"},{"Val":"1.045","Width":"20%"},{"Val":"0.20","Width":"20%"}]]}]},{"Title":"BOIL","Stats":[{"Item1":"Boil Time(mins)","Item2":"60"}],"Tables":[{"Title":"Boil Steps","Cols":[{"Val":"Step","Width":"40%"},{"Val":"Temp(째F)","Width":"20%"},{"Val":"Time(mins)","Width":"20%"},{"Val":"Ramp","Width":"20%"}],"Rows":[[{"Val":"Adjunct 1","Width":"40%"},{"Val":"207","Width":"20%"},{"Val":"60","Width":"20%"},{"Val":"Yes","Width":"20%"}],[{"Val":"Adjunct 2","Width":"40%"},{"Val":"207","Width":"20%"},{"Val":"15","Width":"20%"},{"Val":"No","Width":"20%"}],[{"Val":"Adjunct 3","Width":"40%"},{"Val":"207","Width":"20%"},{"Val":"10","Width":"20%"},{"Val":"No","Width":"20%"}],[{"Val":"Adjunct 4","Width":"40%"},{"Val":"207","Width":"20%"},{"Val":"5","Width":"20%"},{"Val":"No","Width":"20%"}]]},{"Title":"Hops","Cols":[{"Val":"Ingredient","Width":"40%"},{"Val":"Amount(oz)","Width":"20%"},{"Val":"AA(%)","Width":"20%"},{"Val":"Time(mins)","Width":"20%"}],"Rows":[[{"Val":"Challenger","Width":"40%"},{"Val":"0.5","Width":"20%"},{"Val":"7.2","Width":"20%"},{"Val":"60","Width":"20%"}],[{"Val":"Styrian Goldings","Width":"40%"},{"Val":"0.5","Width":"20%"},{"Val":"5.25","Width":"20%"},{"Val":"15","Width":"20%"}],[{"Val":"Other (See Notes)","Width":"40%"},{"Val":"0.001","Width":"20%"},{"Val":"0.00","Width":"20%"},{"Val":"10","Width":"20%"}],[{"Val":"Saaz","Width":"40%"},{"Val":"0.25","Width":"20%"},{"Val":"3.5","Width":"20%"},{"Val":"5","Width":"20%"}],[{"Val":"Challenger","Width":"40%"},{"Val":"0.25","Width":"20%"},{"Val":"7.2","Width":"20%"},{"Val":"5","Width":"20%"}]]}]},{"Title":"FERMENTATION","Stats":[{"Item1":"Fermentation Type","Item2":"Ale"}],"Tables":[{"Title":"Yeast","Cols":[{"Val":"Name","Width":"40%"},{"Val":"Expected AA%","Width":"20%"},{"Val":"Range Temp(째F)","Width":"20%"},{"Val":"Pitch Temp(mins)","Width":"20%"}],"Rows":[[{"Val":"Wyeast Belgian Abbey II 1762","Width":"40%"},{"Val":"75","Width":"20%"},{"Val":"65 - 75","Width":"20%"},{"Val":"70","Width":"20%"}]]},{"Title":"Fermentation Steps","Cols":[{"Val":"Step","Width":"40%"},{"Val":"Temp(째F)","Width":"20%"},{"Val":"Days","Width":"20%"},{"Val":"Hours","Width":"20%"}],"Rows":[[{"Val":"Fermentation","Width":"40%"},{"Val":"70","Width":"20%"},{"Val":"10","Width":"20%"},{"Val":"0","Width":"20%"}],[{"Val":"Crash Chill","Width":"40%"},{"Val":"44","Width":"20%"},{"Val":"0","Width":"20%"},{"Val":"0","Width":"20%"}]]}]}],"Stats":{"OG":"1.088","FG":"1.022","IBU":"24","SRM":"13","ABV":"8.6%"},"Style":"BJCP 2008 : 18.E Belgian Dark Strong Ale","SpecialBrewingInstructions":"Place 1/3 tablet of Whirfloc into third hops cage (10 minutes of boil).\nAdd Belgian Candi Sugar into keg at 40 minute point of first hops (20 minutes of boil).","AverageRating":9.0,"NumRatings":1,"Reviews":[]},"OwnedByUser":false,"OwnedByPicoBrew":false,"CanAccess":true,"IsAdmin":false,"AdminView":false,"RedirectURL":null,"PicoBrew_ProfileID":0,"User_ProfileID":0,"UserRated":false,"UserCommented":false,"UserRating":null,"CompartmentNames":{"adjunct":{"0":"Pass Through","2":"Adjunct 1","3":"Adjunct 2","4":"Adjunct 3","5":"Adjunct 4"},"step":{"0":"Pass Through","2":"Adjunct 1","3":"Adjunct 2","4":"Adjunct 3","5":"Adjunct 4","1":"Mash","6":"Pause"}}}}